{
    "http://framist-bucket-openread.oss-cn-shanghai.aliyuncs.com/img/2023/08/15/20230815204012.png": "2023-09-22T16:00:53+08:00",
    "http://clash.razord.top": "2023-09-22T16:00:53+08:00",
    "https://blog.zzsqwq.cn/posts/how-to-use-clash-on-linux": "2023-09-22T16:00:53+08:00",
    "https://a76yyyy.github.io/clash/zh_CN/introduction/service.html": "2023-09-22T16:00:54+08:00",
    "https://letsencrypt.org/zh-cn": "2023-09-22T16:00:54+08:00",
    "https://github.com/treehollow/install-doc": "2023-09-22T16:00:54+08:00",
    "http://www.navicat.com.cn/sponsorship/education/student": "2023-09-22T16:00:55+08:00",
    "https://www.jianshu.com/p/4e761ec96f67": "2023-09-22T16:00:55+08:00",
    "https://letsencrypt.org/images/letsencrypt-logo-horizontal.svg": "2023-09-22T16:00:55+08:00",
    "https://ld246.com/article/1668443267350": "2023-09-22T16:00:55+08:00",
    "https://loafing.cn/posts/hexo-tags.html": "2023-09-22T16:00:55+08:00",
    "https://www.cnblogs.com/yangstar/articles/16690342.html": "2023-09-22T16:00:56+08:00",
    "https://cloud.tencent.com/developer/article/1558240": "2023-09-22T16:00:56+08:00",
    "https://www.bilibili.com/read/cv3372025": "2023-09-22T16:00:56+08:00",
    "https://help.aliyun.com/document_detail/31837.html": "2023-09-22T16:00:56+08:00",
    "http://yacd.haishan.me": "2023-09-22T16:00:56+08:00",
    "https://blog.csdn.net/arttnba3/article/details/101465012": "2023-09-22T16:00:56+08:00",
    "https://kyriota.com": "2023-09-22T16:00:57+08:00",
    "https://space.bilibili.com/11955810": "2023-09-22T16:00:59+08:00",
    "https://myxdu.moefactory.com": "2023-09-22T16:00:59+08:00",
    "https://moefactory.com": "2023-09-22T16:00:59+08:00",
    "https://gitee.com/mmdjiji": "2023-09-22T16:00:59+08:00",
    "https://github.com/xhc1111": "2023-09-22T16:01:00+08:00",
    "https://me.csdn.net/zimuzi2019": "2023-09-22T16:01:00+08:00",
    "https://github.com/mmdjiji": "2023-09-22T16:01:00+08:00",
    "https://gitee.com/flukehn/projects": "2023-09-22T16:01:02+08:00",
    "https://blackbird-bb.github.io": "2023-09-22T16:01:02+08:00",
    "https://noahtie.github.io": "2023-09-22T16:01:02+08:00",
    "http://wpa.qq.com/msgrd?v=3": "2023-09-22T16:01:02+08:00",
    "https://blog.csdn.net/qq_45819626": "2023-09-22T16:01:03+08:00",
    "https://arttnba3.cn": "2023-09-22T16:01:03+08:00",
    "https://blog.frankli.site": "2023-09-22T16:01:04+08:00",
    "https://github.com/Robotxm": "2023-09-22T16:01:05+08:00",
    "https://eqqie.cn": "2023-09-22T16:01:13+08:00",
    "https://cor1e.cn": "2023-09-22T16:01:13+08:00",
    "https://stackoverflow.com/users/13389180/arttnba3": "2023-09-22T16:01:14+08:00",
    "https://blog.csdn.net/arttnba3": "2023-09-22T16:01:14+08:00",
    "https://shal10w.github.io": "2023-09-22T16:01:14+08:00",
    "https://github.com/arttnba3": "2023-09-22T16:01:14+08:00",
    "https://github.com/Reverier-Xu/ICTFE": "2023-09-22T16:01:15+08:00",
    "https://www.wootec.top": "2023-09-22T16:01:17+08:00",
    "https://pic3.zhimg.com/84760690a49f47d2581945e4ea6e40f8_xll.jpg": "2023-09-22T16:01:44+08:00",
    "https://ll1ng.github.io": "2023-09-22T16:01:44+08:00",
    "https://profile.csdnimg.cn/0/B/4/1_zimuzi2019": "2023-09-22T16:01:44+08:00",
    "https://luoq1an.github.io": "2023-09-22T16:01:44+08:00",
    "https://github.com/XDSEC": "2023-09-22T16:01:44+08:00",
    "https://www.xdsec.org": "2023-09-22T16:01:45+08:00",
    "https://portrait.gitee.com/uploads/avatars/user/534/1603983_flukehn_1578955715.png": "2023-09-22T16:01:45+08:00",
    "https://img-blog.csdnimg.cn/20191213225923406.png?x-oss-process=image/watermark": "2023-09-22T16:01:45+08:00",
    "https://img-blog.csdnimg.cn/20200415224103551.png?x-oss-process=image/watermark": "2023-09-22T16:01:45+08:00",
    "https://img-blog.csdnimg.cn/20200107140224505.png?x-oss-process=image/watermark": "2023-09-22T16:01:45+08:00",
    "https://img-blog.csdnimg.cn/20191013172912764.png?x-oss-process=image/watermark": "2023-09-22T16:01:45+08:00",
    "https://img-blog.csdnimg.cn/20200901200647434.png?x-oss-process=image/watermark": "2023-09-22T16:01:45+08:00",
    "https://img-blog.csdnimg.cn/20200823200211310.png?x-oss-process=image/watermark": "2023-09-22T16:01:45+08:00",
    "https://img-blog.csdnimg.cn/20200415223648847.png?x-oss-process=image/watermark": "2023-09-22T16:01:45+08:00",
    "https://img-blog.csdnimg.cn/20200521000306872.png?x-oss-process=image/watermark": "2023-09-22T16:01:45+08:00",
    "https://pytorch.apachecn.org": "2023-09-22T16:01:46+08:00",
    "https://pic4.zhimg.com/80/v2-88416c9fe415edf3f84276f7fc25de27.png": "2023-09-22T16:01:46+08:00",
    "https://pic4.zhimg.com/80/v2-0229e337eb704cdace41e17a1bf83657.png": "2023-09-22T16:01:46+08:00",
    "https://pic4.zhimg.com/80/v2-c4d381dfa5116c4902dc6a9f3aceff1f.png": "2023-09-22T16:01:46+08:00",
    "https://pic4.zhimg.com/80/v2-f4ee18c79b4c3aefc84ab7e3f5ae286d.png": "2023-09-22T16:01:46+08:00",
    "https://pic4.zhimg.com/80/v2-6d35282cb55285db78fd1136700e3ec3.png": "2023-09-22T16:01:47+08:00",
    "https://pic4.zhimg.com/80/v2-7012d2d0f8fd78276942463fbfeb9a4b.gif": "2023-09-22T16:01:47+08:00",
    "https://zhuanlan.zhihu.com/p/50449900": "2023-09-22T16:01:47+08:00",
    "https://pic4.zhimg.com/80/v2-8d679d311e057dc178fb5bc1f8f80043.png": "2023-09-22T16:01:47+08:00",
    "https://blog.csdn.net/weixin_47102975/article/details/108253584": "2023-09-22T16:01:47+08:00",
    "https://baike.baidu.com/item/%E6%9F%AF%E9%87%8C%E5%8C%96/10350525": "2023-09-22T16:03:19+08:00",
    "https://blog.csdn.net/Joyyang_c/article/details/108486172": "2023-09-22T16:03:20+08:00",
    "https://cs61a.org": "2023-09-22T16:03:20+08:00",
    "https://cs61a.org/lecture/lec09": "2023-09-22T16:03:20+08:00",
    "https://cs61a.org/lecture/lec12": "2023-09-22T16:03:41+08:00",
    "https://cs61a.org/lecture/lec11": "2023-09-22T16:03:42+08:00",
    "https://cs61a.org/lecture/lec10": "2023-09-22T16:03:42+08:00",
    "https://cloud.tencent.com/developer/article/1406302": "2023-09-22T16:03:42+08:00",
    "https://cs61a.org/lecture/lec14": "2023-09-22T16:03:42+08:00",
    "https://cs61a.org/lecture/lec15": "2023-09-22T16:03:43+08:00",
    "https://cs61a.org/lecture/lec21": "2023-09-22T16:03:43+08:00",
    "https://cs61a.org/lecture/lec16": "2023-09-22T16:03:43+08:00",
    "https://cs61a.org/lecture/lec13": "2023-09-22T16:03:43+08:00",
    "https://cs61a.org/lecture/lec20": "2023-09-22T16:03:43+08:00",
    "https://cs61a.org/lecture/lec19": "2023-09-22T16:03:43+08:00",
    "https://cs61a.org/lecture/lec17": "2023-09-22T16:03:43+08:00",
    "https://cs61a.org/lecture/lec18": "2023-09-22T16:03:43+08:00",
    "https://docs.python.org/zh-cn/3/reference/datamodel.html": "2023-09-22T16:03:43+08:00",
    "https://docs.python.org/3/reference/datamodel.html": "2023-09-22T16:03:44+08:00",
    "https://cs61a.org/lecture/lec28": "2023-09-22T16:03:44+08:00",
    "https://cs61a.org/lecture/lec24": "2023-09-22T16:03:44+08:00",
    "https://cs61a.org/lecture/lec25": "2023-09-22T16:03:44+08:00",
    "https://cs61a.org/lecture/lec23": "2023-09-22T16:03:44+08:00",
    "https://cs61a.org/lecture/lec27": "2023-09-22T16:03:44+08:00",
    "https://cs61a.org/lecture/lec26": "2023-09-22T16:03:44+08:00",
    "https://cs61a.org/lecture/lec22": "2023-09-22T16:03:44+08:00",
    "https://www.jianshu.com/p/376e433214b3": "2023-09-22T16:03:44+08:00",
    "https://zhuanlan.zhihu.com/p/549183520": "2023-09-22T16:03:45+08:00",
    "https://cs61a.org/lecture/lec29": "2023-09-22T16:03:45+08:00",
    "https://cs61a.org/lecture/lec32": "2023-09-22T16:03:45+08:00",
    "https://cs61a.org/lecture/lec33": "2023-09-22T16:03:45+08:00",
    "https://cs61a.org/lecture/lec34": "2023-09-22T16:03:45+08:00",
    "https://cs61a.org/lecture/lec30": "2023-09-22T16:03:46+08:00",
    "https://cs61a.org/lecture/lec31": "2023-09-22T16:03:46+08:00",
    "https://inst.eecs.berkeley.edu": "2023-09-22T16:05:23+08:00",
    "https://code.cs61a.org/fa22/proj/scheme_gallery/entries/ea7072ed/contest.scm": "2023-09-22T16:05:23+08:00",
    "https://cs61a.org/assets/pdfs/61a-mt1-study-guide.pdf": "2023-09-22T16:05:24+08:00",
    "https://cs61a.org/lecture/lec36": "2023-09-22T16:05:24+08:00",
    "https://cs61a.org/lecture/lec38": "2023-09-22T16:05:24+08:00",
    "https://cs61a.org/lecture/lec39": "2023-09-22T16:05:24+08:00",
    "https://cs61a.org/lecture/lec35": "2023-09-22T16:05:24+08:00",
    "https://cs61a.org/lecture/lec37": "2023-09-22T16:05:25+08:00",
    "http://framist-bucket-openread.oss-cn-shanghai.aliyuncs.com/img/2023/09/16/20230916224410.png": "2023-09-22T16:06:54+08:00",
    "http://framist-bucket-openread.oss-cn-shanghai.aliyuncs.com/img/2023/09/16/20230916224402.png": "2023-09-22T16:06:54+08:00",
    "http://framist-bucket-openread.oss-cn-shanghai.aliyuncs.com/img/2023/09/16/20230916224408.png": "2023-09-22T16:06:54+08:00",
    "http://framist-bucket-openread.oss-cn-shanghai.aliyuncs.com/img/2023/09/16/20230916224339.png": "2023-09-22T16:06:54+08:00",
    "http://framist-bucket-openread.oss-cn-shanghai.aliyuncs.com/img/2023/09/16/20230916224413.png": "2023-09-22T16:06:54+08:00",
    "http://framist-bucket-openread.oss-cn-shanghai.aliyuncs.com/img/2023/09/16/20230916224417.png": "2023-09-22T16:06:54+08:00",
    "https://img-blog.csdnimg.cn/img_convert/10d0a70af601faaef4d90fdde0edc4d3.png": "2023-09-22T16:06:54+08:00",
    "https://img-blog.csdnimg.cn/img_convert/7308ebe2af73b93cf8f630b19e1741ea.png": "2023-09-22T16:06:54+08:00",
    "https://zhuanlan.zhihu.com/p/456110373": "2023-09-22T16:06:54+08:00",
    "https://cs61a.org/assets/pdfs/61a-mt2-study-guide.pdf": "2023-09-22T16:06:54+08:00",
    "http://framist-bucket-openread.oss-cn-shanghai.aliyuncs.com/img/2023/09/16/20230916224427.png": "2023-09-22T16:06:54+08:00",
    "http://framist-bucket-openread.oss-cn-shanghai.aliyuncs.com/img/2023/09/16/20230916224434.png": "2023-09-22T16:06:54+08:00",
    "http://framist-bucket-openread.oss-cn-shanghai.aliyuncs.com/img/2023/09/16/20230916224435.png": "2023-09-22T16:06:54+08:00",
    "http://framist-bucket-openread.oss-cn-shanghai.aliyuncs.com/img/2023/09/16/20230916224430.png": "2023-09-22T16:06:54+08:00",
    "http://framist-bucket-openread.oss-cn-shanghai.aliyuncs.com/img/2023/09/16/20230916224421.png": "2023-09-22T16:06:54+08:00",
    "http://framist-bucket-openread.oss-cn-shanghai.aliyuncs.com/img/2023/09/16/20230916224423.png": "2023-09-22T16:06:54+08:00",
    "http://framist-bucket-openread.oss-cn-shanghai.aliyuncs.com/img/2023/09/16/20230916224437.png": "2023-09-22T16:06:54+08:00",
    "http://framist-bucket-openread.oss-cn-shanghai.aliyuncs.com/img/2023/09/16/20230916224441.png": "2023-09-22T16:06:54+08:00",
    "http://framist-bucket-openread.oss-cn-shanghai.aliyuncs.com/img/2023/09/16/20230916224451.png": "2023-09-22T16:06:54+08:00",
    "http://framist-bucket-openread.oss-cn-shanghai.aliyuncs.com/img/2023/09/16/20230916224453.png": "2023-09-22T16:06:54+08:00",
    "http://framist-bucket-openread.oss-cn-shanghai.aliyuncs.com/img/2023/09/16/20230916224517.png": "2023-09-22T16:06:55+08:00",
    "http://framist-bucket-openread.oss-cn-shanghai.aliyuncs.com/img/2023/09/16/20230916224455.png": "2023-09-22T16:06:55+08:00",
    "http://framist-bucket-openread.oss-cn-shanghai.aliyuncs.com/img/2023/09/16/20230916224519.png": "2023-09-22T16:06:55+08:00",
    "http://framist-bucket-openread.oss-cn-shanghai.aliyuncs.com/img/2023/09/16/20230916224524.png": "2023-09-22T16:06:55+08:00",
    "https://img-blog.csdnimg.cn/img_convert/c4156746436905597eaab5ab6617ece7.png": "2023-09-22T16:06:55+08:00",
    "http://framist-bucket-openread.oss-cn-shanghai.aliyuncs.com/img/2023/09/16/20230916224521.png": "2023-09-22T16:06:55+08:00",
    "https://img-blog.csdnimg.cn/img_convert/313ad8dd7623fb62bf83dd95b1a55de5.png": "2023-09-22T16:06:55+08:00",
    "https://img-blog.csdnimg.cn/img_convert/7b92163429e37527b201c5b77bb0f6fe.png": "2023-09-22T16:06:55+08:00",
    "https://img-blog.csdnimg.cn/img_convert/bc1ead7ca41fb3c714c694f990b5bb60.png": "2023-09-22T16:06:55+08:00",
    "https://img-blog.csdnimg.cn/img_convert/fef082fbd632a7d4f4c778329fbcb499.png": "2023-09-22T16:06:55+08:00",
    "https://img-blog.csdnimg.cn/img_convert/d83dc17da00884882e3e13311fc83b99.png": "2023-09-22T16:06:55+08:00",
    "https://img-blog.csdnimg.cn/img_convert/00c34bc5916147aa4badbb6084004497.png": "2023-09-22T16:06:55+08:00",
    "https://img-blog.csdnimg.cn/img_convert/a5ad0226f282b300085d0ad4919f7143.png": "2023-09-22T16:06:55+08:00",
    "https://img-blog.csdnimg.cn/img_convert/140a108570eba1c150fef39e5bf57ce4.png": "2023-09-22T16:06:55+08:00",
    "https://img-blog.csdnimg.cn/img_convert/ff762062140452e6b4b22cbd6c2f6a38.png": "2023-09-22T16:06:55+08:00",
    "https://img-blog.csdnimg.cn/img_convert/bc59bda258efaca0124c4661d2823129.png": "2023-09-22T16:06:55+08:00",
    "https://img-blog.csdnimg.cn/img_convert/c6181e0184daaa4b3305fd0542bc0e88.png": "2023-09-22T16:06:55+08:00",
    "https://img-blog.csdnimg.cn/img_convert/ac7113bc76a804f013626b7fb580bb83.png": "2023-09-22T16:06:55+08:00",
    "https://img-blog.csdnimg.cn/img_convert/9fe397d5554757f97a1a457c2534deac.png": "2023-09-22T16:06:55+08:00",
    "https://img-blog.csdnimg.cn/img_convert/a1c3a8a98ff1a7e05ba57b4e21d56d21.png": "2023-09-22T16:06:55+08:00",
    "https://img-blog.csdnimg.cn/img_convert/90274b84909437823fa352c6bf99df45.png": "2023-09-22T16:06:55+08:00",
    "https://img-blog.csdnimg.cn/img_convert/4bdb266250b1ffa4c381ad060333f770.png": "2023-09-22T16:06:55+08:00",
    "https://img-blog.csdnimg.cn/img_convert/a022b4f47f9641cee856100b898074a2.png": "2023-09-22T16:06:55+08:00",
    "https://img-blog.csdnimg.cn/img_convert/8048d54bb88f5bb6c8e5ed353233adce.png": "2023-09-22T16:06:55+08:00",
    "https://img-blog.csdnimg.cn/img_convert/4a9554af6e262425623b75624659a8ad.png": "2023-09-22T16:06:55+08:00",
    "https://img-blog.csdnimg.cn/img_convert/e61d2b2cfe06292cc2cc5f4c6fea3a09.png": "2023-09-22T16:06:55+08:00",
    "https://img-blog.csdnimg.cn/img_convert/fffb88b8ad9d85b9dbe0f3e9c326fc52.png": "2023-09-22T16:06:55+08:00",
    "https://img-blog.csdnimg.cn/img_convert/e3d43b104c644f5069c685d579e50a63.png": "2023-09-22T16:06:55+08:00",
    "https://img-blog.csdnimg.cn/img_convert/f72b467cd3e02b9459a390a035ffaceb.png": "2023-09-22T16:06:55+08:00",
    "https://img-blog.csdnimg.cn/img_convert/9809599ed55640a3a83147c5de645414.png": "2023-09-22T16:06:55+08:00",
    "https://img-blog.csdnimg.cn/img_convert/5bdaaa750201c421fe1d2e893ab4f80f.png": "2023-09-22T16:06:55+08:00",
    "https://img-blog.csdnimg.cn/img_convert/0ad65f1812afa31c68de42e5bac1d59a.png": "2023-09-22T16:06:55+08:00",
    "https://img-blog.csdnimg.cn/img_convert/6d6f347dffd8f1635d4636cbe0b7cb17.png": "2023-09-22T16:06:55+08:00",
    "https://img-blog.csdnimg.cn/img_convert/7505609552dfff4c1cc234aa20304031.png": "2023-09-22T16:06:55+08:00",
    "https://img-blog.csdnimg.cn/img_convert/7d8ca3f682c159d43f27a147069c844f.png": "2023-09-22T16:06:55+08:00",
    "https://img-blog.csdnimg.cn/img_convert/af3708b68c9e63ba8b66eb8dc060670c.png": "2023-09-22T16:06:55+08:00",
    "https://img-blog.csdnimg.cn/img_convert/fa3d06cfba7008222ed151c2a20d8a5a.png": "2023-09-22T16:06:55+08:00",
    "https://img-blog.csdnimg.cn/img_convert/c7ab37b802c31ee860e8ab43579fbd5c.png": "2023-09-22T16:06:55+08:00",
    "https://img-blog.csdnimg.cn/img_convert/e9ace85cb39913850c98ded5c57387dd.png": "2023-09-22T16:06:55+08:00",
    "https://img-blog.csdnimg.cn/img_convert/294a3229f3ca49de61a14ce31d8366f4.png": "2023-09-22T16:06:56+08:00",
    "http://framist-bucket-openread.oss-cn-shanghai.aliyuncs.com/img/2023/08/15/20230815202632.png": "2023-09-22T16:06:56+08:00",
    "https://img-blog.csdnimg.cn/img_convert/23757e08c2ae6d36a5a7851ff6d7c838.png": "2023-09-22T16:06:56+08:00",
    "https://img-blog.csdnimg.cn/img_convert/28eda904cc9e18900f37f77d9629e77f.png": "2023-09-22T16:06:56+08:00",
    "https://img-blog.csdnimg.cn/img_convert/6250a859515c06dd7d30e67002c2fb7a.png": "2023-09-22T16:06:56+08:00",
    "https://img-blog.csdnimg.cn/img_convert/a3ab6c2a4b2e2a15613e9de62143d362.png": "2023-09-22T16:06:56+08:00",
    "https://img-blog.csdnimg.cn/img_convert/43e53bcf918d3b275ee47ae830a6defa.png": "2023-09-22T16:06:56+08:00",
    "https://baike.baidu.com/item/IEEE": "2023-09-22T16:06:56+08:00",
    "https://www.cnblogs.com/imjustice/p/regex_select_text_in_quota.html": "2023-09-22T16:06:56+08:00",
    "https://blog.csdn.net/weixin_30699831/article/details/98134285": "2023-09-22T16:06:56+08:00",
    "https://pic4.zhimg.com/80/v2-0dca3ea692d738f4a46554955091154f.png": "2023-09-22T16:06:58+08:00",
    "https://www.runoob.com/java/java-modifier-types.html": "2023-09-22T16:06:58+08:00",
    "https://www.cnblogs.com/ysocean/p/8194428.html": "2023-09-22T16:06:58+08:00",
    "https://pic4.zhimg.com/80/v2-dcf06d81221f27d721c89fba66c9b215.png": "2023-09-22T16:06:59+08:00",
    "https://pic4.zhimg.com/80/v2-631e3ac3bd271f292560314dac847970.png": "2023-09-22T16:06:59+08:00",
    "https://pic4.zhimg.com/80/v2-cedb61a2ec668e3d98b6267da427aa8e.png": "2023-09-22T16:06:59+08:00",
    "https://pic4.zhimg.com/80/v2-9575722bd35cd1a431a910ce48ad6ec2.png": "2023-09-22T16:06:59+08:00",
    "https://pic4.zhimg.com/80/v2-087e32c282d006512b97603be07d7449.png": "2023-09-22T16:06:59+08:00",
    "https://www.zhihu.com/question/28414001": "2023-09-22T16:06:59+08:00",
    "https://pic4.zhimg.com/80/v2-c6a002d00784629b5d58dc22f0debba3.png": "2023-09-22T16:06:59+08:00",
    "http://framist-bucket-openread.oss-cn-shanghai.aliyuncs.com/img/2023/08/15/20230815202827-1.png": "2023-09-22T16:06:59+08:00",
    "http://framist-bucket-openread.oss-cn-shanghai.aliyuncs.com/img/2023/08/15/20230815202827.png": "2023-09-22T16:06:59+08:00",
    "https://www.cnblogs.com/zheting/p/7751787.html": "2023-09-22T16:07:00+08:00",
    "https://kb.cnblogs.com/page/42159": "2023-09-22T16:07:00+08:00",
    "https://egraphs-good.github.io": "2023-09-22T16:07:00+08:00",
    "https://blog.csdn.net/tntzs666/article/details/80274526": "2023-09-22T16:07:00+08:00",
    "https://blog.csdn.net/weixin_41954254/article/details/84573341": "2023-09-22T16:07:00+08:00",
    "https://github.com/framist/egg-language-server": "2023-09-22T16:07:22+08:00",
    "https://github.com/framist/egg-language-server/blob/main/doc/slide.pdf": "2023-09-22T16:07:36+08:00",
    "https://www.jianshu.com/p/c70afbbf5172": "2023-09-22T16:07:36+08:00",
    "https://zhuanlan.zhihu.com/p/128972800": "2023-09-22T16:07:36+08:00",
    "https://zhuanlan.zhihu.com/p/138708196": "2023-09-22T16:07:37+08:00",
    "https://www.cnblogs.com/unr4v31/p/15237728.html": "2023-09-22T16:07:37+08:00",
    "https://pic4.zhimg.com/80/v2-160aa1b6ef8ced6ca18584164864428a.png": "2023-09-22T16:07:37+08:00",
    "https://ftp.gnu.org/gnu/coreutils": "2023-09-22T16:07:39+08:00",
    "https://github.com/google/AFL": "2023-09-22T16:07:52+08:00",
    "https://github.com/google/AFL/issues/41": "2023-09-22T16:07:53+08:00",
    "https://pic4.zhimg.com/80/v2-cb546ed4ed95ed9181e6cd02b2e0a992.png": "2023-09-22T16:07:58+08:00",
    "https://pic4.zhimg.com/80/v2-c3921794c8531f3144330d38b582eb6d.png": "2023-09-22T16:07:58+08:00",
    "https://pic4.zhimg.com/80/v2-9d6a939a0ff888895d92a9f851eab5a9.png": "2023-09-22T16:07:58+08:00",
    "https://pic4.zhimg.com/80/v2-9924f1d1d9f2889e83b6d2c26b36fa68.png": "2023-09-22T16:07:58+08:00",
    "https://pic4.zhimg.com/80/v2-6ee1a096bb91fef327ea4f6c3cbe49a5.png": "2023-09-22T16:07:58+08:00",
    "https://pic4.zhimg.com/80/v2-10b711cc70208930f7b5e82c0919c982.png": "2023-09-22T16:07:58+08:00",
    "https://pic4.zhimg.com/80/v2-85dcacc94fa813e3973829d812ba2c78.png": "2023-09-22T16:07:58+08:00",
    "http://framist-bucket-openread.oss-cn-shanghai.aliyuncs.com/img/2023/08/15/20230815203735.png": "2023-09-22T16:07:58+08:00",
    "https://www.zhihu.com/question/50735753%EF%BC%8C%E7%9C%8B%E6%87%82%EF%BC%8C%E6%83%B3%E6%83%B3%EF%BC%8C%E6%9C%89%E6%83%B3%E6%B3%95%E5%86%99%E5%87%BA%E6%9D%A5%EF%BC%8C%E5%81%9A%E4%B8%80%E4%B8%AA%E5%A5%BD%E7%8E%A9%E7%9A%84%E4%B8%9C%E8%A5%BF%E3%80%82": "2023-09-22T16:07:58+08:00",
    "https://blog.csdn.net/youkawa/article/details/45696317": "2023-09-22T16:07:59+08:00",
    "http://framist-bucket-openread.oss-cn-shanghai.aliyuncs.com/img/2023/08/15/20230815203735-1.png": "2023-09-22T16:07:59+08:00",
    "http://framist-bucket-openread.oss-cn-shanghai.aliyuncs.com/img/2023/08/15/20230815203735-7.png": "2023-09-22T16:07:59+08:00",
    "http://framist-bucket-openread.oss-cn-shanghai.aliyuncs.com/img/2023/08/15/20230815203735-2.png": "2023-09-22T16:07:59+08:00",
    "http://framist-bucket-openread.oss-cn-shanghai.aliyuncs.com/img/2023/08/15/20230815203735-8.png": "2023-09-22T16:07:59+08:00",
    "http://framist-bucket-openread.oss-cn-shanghai.aliyuncs.com/img/2023/08/15/20230815203735-3.png": "2023-09-22T16:07:59+08:00",
    "http://framist-bucket-openread.oss-cn-shanghai.aliyuncs.com/img/2023/08/15/20230815203735-4.png": "2023-09-22T16:07:59+08:00",
    "http://framist-bucket-openread.oss-cn-shanghai.aliyuncs.com/img/2023/08/15/20230815203735-9.png": "2023-09-22T16:07:59+08:00",
    "http://framist-bucket-openread.oss-cn-shanghai.aliyuncs.com/img/2023/08/15/20230815203735-5.png": "2023-09-22T16:07:59+08:00",
    "http://framist-bucket-openread.oss-cn-shanghai.aliyuncs.com/img/2023/08/15/20230815203735-6.png": "2023-09-22T16:07:59+08:00",
    "http://framist-bucket-openread.oss-cn-shanghai.aliyuncs.com/img/2023/08/15/20230815203735-10.png": "2023-09-22T16:07:59+08:00",
    "https://pic4.zhimg.com/80/v2-dcb8344c0cef2387de09c0cb09d2ef9a.png": "2023-09-22T16:07:59+08:00",
    "http://framist-bucket-openread.oss-cn-shanghai.aliyuncs.com/img/2023/08/15/20230815203735-11.png": "2023-09-22T16:07:59+08:00",
    "http://framist-bucket-openread.oss-cn-shanghai.aliyuncs.com/img/2023/08/15/20230815203735-15.png": "2023-09-22T16:07:59+08:00",
    "https://pic4.zhimg.com/80/v2-0e60b052374c3fd7346f63038f2eeee2.png": "2023-09-22T16:07:59+08:00",
    "http://framist-bucket-openread.oss-cn-shanghai.aliyuncs.com/img/2023/08/15/20230815203735-12.png": "2023-09-22T16:07:59+08:00",
    "http://framist-bucket-openread.oss-cn-shanghai.aliyuncs.com/img/2023/08/15/20230815203735-13.png": "2023-09-22T16:07:59+08:00",
    "http://framist-bucket-openread.oss-cn-shanghai.aliyuncs.com/img/2023/08/15/20230815203735-14.png": "2023-09-22T16:07:59+08:00",
    "https://pic4.zhimg.com/80/v2-f70355e9b21a046d4a4d14bf10afda1b.png": "2023-09-22T16:07:59+08:00",
    "https://pic4.zhimg.com/80/v2-b4455bce590447cef244d9e57958c46f.png": "2023-09-22T16:07:59+08:00",
    "https://zhuanlan.zhihu.com/p/25816426": "2023-09-22T16:07:59+08:00",
    "https://pic4.zhimg.com/80/v2-b5407396c2ff2b8d1e65b264d54d3946.png": "2023-09-22T16:07:59+08:00",
    "https://pic4.zhimg.com/80/v2-b0af314ae3428f74a0c5ec9048d3c50b.png": "2023-09-22T16:07:59+08:00",
    "https://pic4.zhimg.com/80/v2-23264ae344fdd18b41094c39740cf34e.png": "2023-09-22T16:07:59+08:00",
    "https://pic4.zhimg.com/80/v2-c6ecce330b1057b11ab05a0de5c4cd26.png": "2023-09-22T16:07:59+08:00",
    "https://pic4.zhimg.com/80/v2-0f1f9af9b2980c144516bf180745b237.png": "2023-09-22T16:07:59+08:00",
    "https://zhuanlan.zhihu.com/p/422435352": "2023-09-22T16:08:00+08:00",
    "https://pic4.zhimg.com/80/v2-b1db441310bcbbb05b1e6240bbbcc378.png": "2023-09-22T16:08:00+08:00",
    "https://pic4.zhimg.com/80/v2-2adb7fb01efcb03be07b858b5f2cf3db.png": "2023-09-22T16:08:00+08:00",
    "https://pic4.zhimg.com/80/v2-47bcfc74ea2116b6f5639e6669d6f4ed.png": "2023-09-22T16:08:00+08:00",
    "https://pic4.zhimg.com/80/v2-32a16412a565fc7d3943fbab8f525a93.png": "2023-09-22T16:08:00+08:00",
    "https://pic4.zhimg.com/80/v2-0b5702b41cde45576be4aae8080e3bcf.png": "2023-09-22T16:08:00+08:00",
    "https://pic4.zhimg.com/80/v2-197f88eadcc2aa1ef9c4b0653eebc9f6.png": "2023-09-22T16:08:00+08:00",
    "https://pic4.zhimg.com/80/v2-edd28c786d008d83c7adfd2f96747bd5.png": "2023-09-22T16:08:00+08:00",
    "https://pic4.zhimg.com/80/v2-4c29bd28594d14b151b27a6feef23ac8.png": "2023-09-22T16:08:00+08:00",
    "https://pic4.zhimg.com/80/v2-834e13cd95772958104ef47fae0bdc97.png": "2023-09-22T16:08:00+08:00",
    "https://pic4.zhimg.com/80/v2-511a4137f20a6d79e1084b129614f44a.png": "2023-09-22T16:08:00+08:00",
    "https://pic4.zhimg.com/80/v2-314727e97fe7706d848e9aaaa3bad8d8.png": "2023-09-22T16:08:00+08:00",
    "https://pic4.zhimg.com/80/v2-0f0966e6a4fc3b61c03c16d809d4be2a.png": "2023-09-22T16:08:00+08:00",
    "https://pic4.zhimg.com/80/v2-e5b4573ddf7cf78cdbfad763a9be62e0.png": "2023-09-22T16:08:00+08:00",
    "https://pic4.zhimg.com/80/v2-2b962fecb161624f108e018df71f2ae2.png": "2023-09-22T16:08:01+08:00",
    "https://www.zhihu.com/equation?tex=%5Ctilde%7Bf%7D(t)": "2023-09-22T16:08:01+08:00",
    "https://www.zhihu.com/equation?tex=f(t)": "2023-09-22T16:08:01+08:00",
    "https://pic3.zhimg.com/80/v2-9686261dcb2a46affa2834fd39e49492_720w.jpg": "2023-09-22T16:08:01+08:00",
    "https://pic4.zhimg.com/80/v2-f56d8dc14a909ae67cd6d1ac558c2b56.png": "2023-09-22T16:08:01+08:00",
    "https://pic4.zhimg.com/80/v2-edf65047d624bb952062a52718c6d57c.png": "2023-09-22T16:08:01+08:00",
    "https://pic4.zhimg.com/80/v2-5ed50c762a573a2f71351e5b3706ebff.png": "2023-09-22T16:08:01+08:00",
    "https://pic4.zhimg.com/80/v2-9e565ccfbb80c144a4cc8ab00958080d.png": "2023-09-22T16:08:01+08:00",
    "https://pic4.zhimg.com/80/v2-81263656a43d0af545b0bdd2e923aa74.png": "2023-09-22T16:08:01+08:00",
    "https://pic4.zhimg.com/80/v2-c0b6a6beead48c7eea5523a2460120f1.png": "2023-09-22T16:08:01+08:00",
    "https://pic4.zhimg.com/80/v2-84c2bfc2279afa2d049cc8d11d67a0ac.png": "2023-09-22T16:08:02+08:00",
    "https://pic4.zhimg.com/80/v2-7768b55766f86cb8b376db5c0d89e8ff.png": "2023-09-22T16:08:02+08:00",
    "https://pic4.zhimg.com/80/v2-d346fced8f8dc8556f5eb527ae3b5c28.png": "2023-09-22T16:08:02+08:00",
    "https://pic4.zhimg.com/80/v2-f52ad2583e10381cca65af7aecfc2c07.png": "2023-09-22T16:08:02+08:00",
    "https://pic4.zhimg.com/80/v2-4f603d69e1f2416feb62e57bd69d51e8.png": "2023-09-22T16:08:02+08:00",
    "https://pic4.zhimg.com/80/v2-04c461f6327fb597a5f7cfe07a68b5fc.png": "2023-09-22T16:08:02+08:00",
    "https://pic4.zhimg.com/80/v2-3f2f80008908a475eee213baf7adaa8e.png": "2023-09-22T16:08:02+08:00",
    "https://pic4.zhimg.com/80/v2-23085d84ced1ebc4bdaaa89628e2cd32.png": "2023-09-22T16:08:02+08:00",
    "https://pic4.zhimg.com/80/v2-e22a39525639804d709a524c83976b61.png": "2023-09-22T16:08:02+08:00",
    "https://pic4.zhimg.com/80/v2-080aa7a0fc13d25d15bed190f459db2a.png": "2023-09-22T16:08:02+08:00",
    "https://pic4.zhimg.com/80/v2-276dc3f10155be38831ae7d265de2674.png": "2023-09-22T16:08:02+08:00",
    "https://pic4.zhimg.com/80/v2-0d3ebbe06c63e2ab0494c926e9862f80.png": "2023-09-22T16:08:02+08:00",
    "https://pic4.zhimg.com/80/v2-6d2d5cbb51990001e0f083b592be0ff3.png": "2023-09-22T16:08:02+08:00",
    "https://pic4.zhimg.com/80/v2-60a186791f3f90143d77eb3b33e8af67.png": "2023-09-22T16:08:02+08:00",
    "https://pic4.zhimg.com/80/v2-7b835d916773e8223c63b2768e22ac3a.png": "2023-09-22T16:08:03+08:00",
    "https://pic4.zhimg.com/80/v2-86aadd3120d289768f98ec52148ac030.png": "2023-09-22T16:08:03+08:00",
    "https://pic4.zhimg.com/80/v2-3d1047d3165e6a9a676d8209cfdf1d71.png": "2023-09-22T16:08:03+08:00",
    "https://pic4.zhimg.com/80/v2-a335636fac6e7e1b1596ad777584c997.png": "2023-09-22T16:08:03+08:00",
    "https://pic4.zhimg.com/80/v2-268459da3a1df410143b5968d430fd71.png": "2023-09-22T16:08:03+08:00",
    "https://pic4.zhimg.com/80/v2-985b11f2946873968e04553118dac3d4.png": "2023-09-22T16:08:03+08:00",
    "https://pic4.zhimg.com/80/v2-3b779e4000c6b9fdf0203ff0e40e6f28.png": "2023-09-22T16:08:03+08:00",
    "https://pic4.zhimg.com/80/v2-15dc3282ab5afaf63d2ab9f878226c23.png": "2023-09-22T16:08:03+08:00",
    "https://pic4.zhimg.com/80/v2-3abed6be9415880d477a54741c5083d2.png": "2023-09-22T16:08:03+08:00",
    "https://pic4.zhimg.com/80/v2-95eee2308230eb8a7adf1778d757672b.png": "2023-09-22T16:08:03+08:00",
    "https://pic4.zhimg.com/80/v2-b34de8f91915c4ddfe6b610bd22705f0.png": "2023-09-22T16:08:03+08:00",
    "https://pic4.zhimg.com/80/v2-ae95a7cd523ba49ef30c4110c691897d.png": "2023-09-22T16:08:03+08:00",
    "https://pic4.zhimg.com/80/v2-ed4d73debaf23c0c05587ea151d17b68.png": "2023-09-22T16:08:03+08:00",
    "https://pic4.zhimg.com/80/v2-2a023c3ce52a16a6d956bc1ef5ea1a59.png": "2023-09-22T16:08:03+08:00",
    "https://pic4.zhimg.com/80/v2-ed989d0080216702f8c4dd46a7a74369.png": "2023-09-22T16:08:03+08:00",
    "https://pic4.zhimg.com/80/v2-3e07313f901c247e46334b5f8e61d874.png": "2023-09-22T16:08:04+08:00",
    "https://pic4.zhimg.com/80/v2-d00e86e9055357609302159775c0136c.png": "2023-09-22T16:08:04+08:00",
    "https://pic4.zhimg.com/80/v2-96d722e11ed676cfeb2043dbfccb2180.png": "2023-09-22T16:08:04+08:00",
    "https://pic4.zhimg.com/80/v2-ce1bb815a89b9e415cbe1110db9cb706.png": "2023-09-22T16:08:04+08:00",
    "https://pic4.zhimg.com/80/v2-eb39531c9be5a25c779ecce3781b1828.png": "2023-09-22T16:08:04+08:00",
    "https://pic4.zhimg.com/80/v2-84c0d970cc597eabb3d33d953ff9e939.png": "2023-09-22T16:08:04+08:00",
    "https://pic4.zhimg.com/80/v2-24fe1971047820d72a890d8c08284963.png": "2023-09-22T16:08:04+08:00",
    "https://pic4.zhimg.com/80/v2-526f9fb605e632cf87f73661e8b3ac7e.png": "2023-09-22T16:08:04+08:00",
    "https://pic4.zhimg.com/80/v2-adc180cc4ea0e309017d941f0d50b95e.png": "2023-09-22T16:08:04+08:00",
    "https://pic4.zhimg.com/80/v2-e7ed60895be223f27ddcc20c9978317a.png": "2023-09-22T16:08:04+08:00",
    "https://pic4.zhimg.com/80/v2-bec8794e128a0d736c0eb6ea0c43e088.png": "2023-09-22T16:08:04+08:00",
    "https://pic4.zhimg.com/80/v2-4075a6d361f3a65a9c15f75a5bf717ce.png": "2023-09-22T16:08:04+08:00",
    "https://pic4.zhimg.com/80/v2-9c8771344195491388470dfa0452fce3.png": "2023-09-22T16:08:04+08:00",
    "https://pic4.zhimg.com/80/v2-69116774033fc92e887fb9ddf81d9f7d.png": "2023-09-22T16:08:04+08:00",
    "https://pic4.zhimg.com/80/v2-dd852f84a668388b2b216bdc60aa71d3.png": "2023-09-22T16:08:05+08:00",
    "https://pic4.zhimg.com/80/v2-cb26212e2db07fff584885f7e9bd6d6e.png": "2023-09-22T16:08:05+08:00",
    "https://pic4.zhimg.com/80/v2-4b53d599ccaa7d77e4175f635e624d37.png": "2023-09-22T16:08:05+08:00",
    "https://pic4.zhimg.com/80/v2-0a0c8c257a117bd49994bedb65c96551.png": "2023-09-22T16:08:05+08:00",
    "https://pic4.zhimg.com/80/v2-09284f7aeb78cff3a501c0cbe4550481.png": "2023-09-22T16:08:05+08:00",
    "https://pic4.zhimg.com/80/v2-cb0b2ff5771e2d4b62a0155e707546cf.png": "2023-09-22T16:08:05+08:00",
    "https://pic4.zhimg.com/80/v2-f219a2a190aab81efdaee58025d84d1f.png": "2023-09-22T16:08:05+08:00",
    "https://pic4.zhimg.com/80/v2-7971f944c2f22236fac03d763d823b3b.png": "2023-09-22T16:08:05+08:00",
    "https://pic4.zhimg.com/80/v2-043d4cbcdcc7260c0487298fa860aa01.png": "2023-09-22T16:08:05+08:00",
    "https://pic4.zhimg.com/80/v2-03023853d99dbb31f981c1fcd4ec8b7f.png": "2023-09-22T16:08:05+08:00",
    "https://pic4.zhimg.com/80/v2-627cddbe74fa5bf19aabdd5daf8da7d6.png": "2023-09-22T16:08:05+08:00",
    "https://pic4.zhimg.com/80/v2-64291a5d735f45b54f4d87458b3b8550.png": "2023-09-22T16:08:05+08:00",
    "https://pic4.zhimg.com/80/v2-395c656a3bcae437fab3efda8f0c048d.png": "2023-09-22T16:08:05+08:00",
    "https://pic4.zhimg.com/80/v2-9ab8fd9a4be871808258e11029538b46.png": "2023-09-22T16:08:05+08:00",
    "https://pic4.zhimg.com/80/v2-43c037fa37447ff81f46d84eef282916.png": "2023-09-22T16:08:05+08:00",
    "https://pic4.zhimg.com/80/v2-12a8a33ddeffd5de13ab1640609e3815.png": "2023-09-22T16:08:05+08:00",
    "https://pic4.zhimg.com/80/v2-bbb439e541abdcf3091b0fed4cf33af7.png": "2023-09-22T16:08:05+08:00",
    "https://pic4.zhimg.com/80/v2-39f36190b153989e64f09a1728272ef5.png": "2023-09-22T16:08:05+08:00",
    "https://pic4.zhimg.com/80/v2-0b3c5a61a7cc73391eac35f53050ac0e.png": "2023-09-22T16:08:05+08:00",
    "https://pic4.zhimg.com/80/v2-78522cd089d8cf6602e954981ce38296.png": "2023-09-22T16:08:06+08:00",
    "https://pic4.zhimg.com/80/v2-769619b67223c7e6c478c4aba9eed1de.png": "2023-09-22T16:08:06+08:00",
    "https://pic4.zhimg.com/80/v2-93682186ed23cf67a946a146a821ed8d.png": "2023-09-22T16:08:06+08:00",
    "https://pic4.zhimg.com/80/v2-5ab9df3ba62f3856c478e8bc7229fe12.png": "2023-09-22T16:08:06+08:00",
    "https://pic4.zhimg.com/80/v2-6e7bc89f2dab4c70c0a028ea9ab3fbbd.png": "2023-09-22T16:08:06+08:00",
    "https://pic4.zhimg.com/80/v2-6b9e5a566d789728333cf669d0b7797b.png": "2023-09-22T16:08:06+08:00",
    "https://pic4.zhimg.com/80/v2-1b58dda48f77d70eb187b29efde8b328.png": "2023-09-22T16:08:06+08:00",
    "https://pic4.zhimg.com/80/v2-799a42a89e613821037b6e14f020ace9.png": "2023-09-22T16:08:06+08:00",
    "https://pic4.zhimg.com/80/v2-64c51073636c9bcfacf5e0390474469d.png": "2023-09-22T16:08:06+08:00",
    "https://pic4.zhimg.com/80/v2-e8a2293548f6df6b5d9deb56d264ec23.png": "2023-09-22T16:08:06+08:00",
    "https://pic4.zhimg.com/80/v2-e0412fe19d35faaa2c6fd90bb3d78f8a.png": "2023-09-22T16:08:06+08:00",
    "https://pic4.zhimg.com/80/v2-2d683a0c77aab39b2e60bfbb9e01ffac.png": "2023-09-22T16:08:06+08:00",
    "https://pic4.zhimg.com/80/v2-abbde05da646f8af0d2d6cba2900e71e.png": "2023-09-22T16:08:06+08:00",
    "https://pic4.zhimg.com/80/v2-951d9adcb853a1d417291315ac957ca9.png": "2023-09-22T16:08:06+08:00",
    "https://pic4.zhimg.com/80/v2-46bb9f92b2af43d48df8be6119a9f75f.png": "2023-09-22T16:08:06+08:00",
    "https://pic4.zhimg.com/80/v2-8a4fefe61fcc7e1d2f5446ae27935976.png": "2023-09-22T16:08:06+08:00",
    "https://pic4.zhimg.com/80/v2-900a39c6eec93475c0efbd54f4fa05af.png": "2023-09-22T16:08:06+08:00",
    "https://pic4.zhimg.com/80/v2-900c89329650e1b2dfcc8957da80ea3a.png": "2023-09-22T16:08:06+08:00",
    "https://pic4.zhimg.com/80/v2-c74b730d6bc87f53161939beef094ce0.png": "2023-09-22T16:08:06+08:00",
    "https://pic4.zhimg.com/80/v2-814cb625f442952256c4367bf250712b.png": "2023-09-22T16:08:07+08:00",
    "https://pic4.zhimg.com/80/v2-8d8e1408a34553ebc1d90cc8b535af9a.png": "2023-09-22T16:08:07+08:00",
    "https://pic4.zhimg.com/80/v2-c02732715eee5533848e7911bd37f0c9.png": "2023-09-22T16:08:07+08:00",
    "https://pic4.zhimg.com/80/v2-5fdc01e2d758db5410622c49d6d4dc92.png": "2023-09-22T16:08:07+08:00",
    "https://pic4.zhimg.com/80/v2-43be2536dbd773efd0159bd42911a336.png": "2023-09-22T16:08:07+08:00",
    "https://pic4.zhimg.com/80/v2-f6d5ea7130bded633f74b897dc84ca22.png": "2023-09-22T16:08:07+08:00",
    "https://pic4.zhimg.com/80/v2-2c77a3cafb6bc5a510e35a099f8cc423.png": "2023-09-22T16:08:07+08:00",
    "https://pic4.zhimg.com/80/v2-6588a346686d2aff1b27915567667ee3.png": "2023-09-22T16:08:07+08:00",
    "https://pic4.zhimg.com/80/v2-53cd7b31c83e345c9873d866d2766aaf.png": "2023-09-22T16:08:07+08:00",
    "https://pic4.zhimg.com/80/v2-f5313263c43a7927d5515471c567ff7d.png": "2023-09-22T16:08:07+08:00",
    "https://pic4.zhimg.com/80/v2-1097f1da411a5eea28316b7c72d64e62.png": "2023-09-22T16:08:07+08:00",
    "https://pic4.zhimg.com/80/v2-6b927198e370d15801e99edfb543745f.png": "2023-09-22T16:08:07+08:00",
    "https://pic4.zhimg.com/80/v2-7383f6ada9c84b6b4899ec8d73b58c1f.png": "2023-09-22T16:08:07+08:00",
    "https://pic4.zhimg.com/80/v2-090c0d2704e93c1d6ba033f1b4a87db2.png": "2023-09-22T16:08:07+08:00",
    "https://pic4.zhimg.com/80/v2-7bf1dceb8e15e33c06207e77d490ba60.png": "2023-09-22T16:08:07+08:00",
    "https://pic4.zhimg.com/80/v2-039131b2651713e9871b1504c4f50238.png": "2023-09-22T16:08:07+08:00",
    "https://pic4.zhimg.com/80/v2-86917df190899c30a1d7220890d0cb9b.png": "2023-09-22T16:08:07+08:00",
    "https://pic4.zhimg.com/80/v2-3bb65c710867f5bdf0f6d2ec23e817ac.png": "2023-09-22T16:08:07+08:00",
    "https://pic4.zhimg.com/80/v2-81b7e95d44fa2ffa77fa8a653ed1b5b9.png": "2023-09-22T16:08:07+08:00",
    "https://pic4.zhimg.com/80/v2-575d072de2124b329646201d20c0af32.png": "2023-09-22T16:08:08+08:00",
    "https://pic4.zhimg.com/80/v2-a0ec23746c40448d7f37751ca27049b7.png": "2023-09-22T16:08:08+08:00",
    "https://pic4.zhimg.com/80/v2-b3f92e6d0aa802bbf8c62346bd071a28.png": "2023-09-22T16:08:08+08:00",
    "https://pic4.zhimg.com/80/v2-065969b9bdf36c0687b7fb8373ce6512.png": "2023-09-22T16:08:08+08:00",
    "https://pic4.zhimg.com/80/v2-5e956aa40ff823bdc940890af8021c7d.png": "2023-09-22T16:08:08+08:00",
    "https://pic4.zhimg.com/80/v2-2f5c64dabf0b0c5b56d2f74a5af0976d.png": "2023-09-22T16:08:08+08:00",
    "https://pic4.zhimg.com/80/v2-9a64b088e1e5a9f27d7831393d398d24.png": "2023-09-22T16:08:08+08:00",
    "https://pic4.zhimg.com/80/v2-8f8dff8951c2ffe77980a6d0bb6cf805.png": "2023-09-22T16:08:08+08:00",
    "https://pic4.zhimg.com/80/v2-bc5eb224e42d4207f563a3399f258e1f.png": "2023-09-22T16:08:08+08:00",
    "https://pic4.zhimg.com/80/v2-fdc2a684fbfe8ea3dfb4d44b35452db2.png": "2023-09-22T16:08:08+08:00",
    "https://pic4.zhimg.com/80/v2-f79866e718c04bf9f7ca76baeb9bd674.png": "2023-09-22T16:08:08+08:00",
    "https://pic4.zhimg.com/80/v2-9c83a08545df09f9be2cfd933557ae97.png": "2023-09-22T16:08:08+08:00",
    "https://pic4.zhimg.com/80/v2-3767d181f8d537d3f55b4cf4654328ce.png": "2023-09-22T16:08:09+08:00",
    "https://pic4.zhimg.com/80/v2-a0c5952367302e372d6e8b85f0dcfa35.png": "2023-09-22T16:08:09+08:00",
    "https://pic4.zhimg.com/80/v2-42861f6214eecf546d83af92e9845d19.png": "2023-09-22T16:08:09+08:00",
    "https://pic4.zhimg.com/80/v2-e195cbe519815b9514896ed0d4a464d1.png": "2023-09-22T16:08:09+08:00",
    "https://pic4.zhimg.com/80/v2-3e679cead560876da24e2c849a455ca9.png": "2023-09-22T16:08:09+08:00",
    "https://pic4.zhimg.com/80/v2-7ae2de6628f29b2bcc516fb3f3488fc5.png": "2023-09-22T16:08:09+08:00",
    "https://pic4.zhimg.com/80/v2-08e7173c7d51b9b8089e5da6b28f5179.png": "2023-09-22T16:08:09+08:00",
    "https://pic4.zhimg.com/80/v2-52ef097abc1dd2cc455d169b783e4112.png": "2023-09-22T16:08:09+08:00",
    "https://pic4.zhimg.com/80/v2-8bea82d60ffac6e5f78dfd77ec2f7516.png": "2023-09-22T16:08:09+08:00",
    "https://pic4.zhimg.com/80/v2-51b6a41fba2ff6cf0e3080277d39d673.png": "2023-09-22T16:08:09+08:00",
    "https://pic4.zhimg.com/80/v2-88e5099c4b575865fa722e470fa19d3d.png": "2023-09-22T16:08:09+08:00",
    "https://pic4.zhimg.com/80/v2-300b39dfe1349def8f18a2fd0a7a09be.png": "2023-09-22T16:08:09+08:00",
    "https://pic4.zhimg.com/80/v2-15fb49fa1ce1dafbf7a6ebec5210d0f4.png": "2023-09-22T16:08:09+08:00",
    "https://pic4.zhimg.com/80/v2-2331df6373e911cf106ad2e0dec2c370.png": "2023-09-22T16:08:09+08:00",
    "https://pic4.zhimg.com/80/v2-71c2dc6faa8f090ebe52ec429d26bca6.png": "2023-09-22T16:08:09+08:00",
    "https://pic4.zhimg.com/80/v2-38316e1b93219ba83e7568f842511bd3.png": "2023-09-22T16:08:09+08:00",
    "https://pic4.zhimg.com/80/v2-33a5137145b7f8ddf30b588a405496b5.png": "2023-09-22T16:08:09+08:00",
    "https://pic4.zhimg.com/80/v2-09ab86f63e9f7ba9392f422ed1b77414.png": "2023-09-22T16:08:09+08:00",
    "https://pic4.zhimg.com/80/v2-984332b91978d5538b899c71a8bdec8c.png": "2023-09-22T16:08:09+08:00",
    "https://pic4.zhimg.com/80/v2-d692f6b954d2451e3579cff20e497247.png": "2023-09-22T16:08:10+08:00",
    "https://pic4.zhimg.com/80/v2-84dbebef93e9521e8db3af2a8ad76bc9.png": "2023-09-22T16:08:10+08:00",
    "https://pic4.zhimg.com/80/v2-0ae780692eabee9dcfb773ea20234e9b.png": "2023-09-22T16:08:10+08:00",
    "https://pic4.zhimg.com/80/v2-3248aa7855ac3e3ffd662d8405301d49.png": "2023-09-22T16:08:10+08:00",
    "https://pic4.zhimg.com/80/v2-2d6fc362665e91710c29d76721edfe6c.png": "2023-09-22T16:08:10+08:00",
    "https://pic4.zhimg.com/80/v2-e6c2e54ecf09aeb6fef28be3a09adfb9.png": "2023-09-22T16:08:10+08:00",
    "https://pic4.zhimg.com/80/v2-0873ceb8a8388daacb304790bc7f0578.png": "2023-09-22T16:08:10+08:00",
    "https://pic4.zhimg.com/80/v2-1d0d66d5beeadbda81857596adb38c6b.png": "2023-09-22T16:08:10+08:00",
    "https://pic4.zhimg.com/80/v2-1d3ccc22a62f50695942eef735d6d39c.png": "2023-09-22T16:08:10+08:00",
    "https://pic4.zhimg.com/80/v2-9f2d0470bd69783102b349f6574407b5.png": "2023-09-22T16:08:10+08:00",
    "https://pic4.zhimg.com/80/v2-cdc183eb2e7e04bf0150e1a12d43e01b.png": "2023-09-22T16:08:10+08:00",
    "https://pic4.zhimg.com/80/v2-e7179b7ec6de9cc5d95608cba5775509.png": "2023-09-22T16:08:10+08:00",
    "https://pic4.zhimg.com/80/v2-7e3d7e72e24a4cc505bd608bb029d865.png": "2023-09-22T16:08:10+08:00",
    "https://pic4.zhimg.com/80/v2-12612851c2f85fb8e95c9082a445e020.png": "2023-09-22T16:08:10+08:00",
    "https://pic4.zhimg.com/80/v2-025515efaac8281cb92e694a5a0c12c2.png": "2023-09-22T16:08:10+08:00",
    "https://pic4.zhimg.com/80/v2-d621996227ce5cd651625f5e4906f8b3.png": "2023-09-22T16:08:10+08:00",
    "https://pic4.zhimg.com/80/v2-71af6bf749ac84bdb9505c86c27be3a6.png": "2023-09-22T16:08:10+08:00",
    "https://pic4.zhimg.com/80/v2-ba1b99433358945ded52aec48ac3968f.png": "2023-09-22T16:08:10+08:00",
    "https://pic4.zhimg.com/80/v2-fcba143e9d21f17977473e595fc9f9b6.png": "2023-09-22T16:08:10+08:00",
    "https://pic4.zhimg.com/80/v2-538506dc0db245e0d68f1b7195368176.png": "2023-09-22T16:08:10+08:00",
    "http://framist-bucket-openread.oss-cn-shanghai.aliyuncs.com/img/2023/08/15/20230815203854.jpg": "2023-09-22T16:08:11+08:00",
    "http://framist-bucket-openread.oss-cn-shanghai.aliyuncs.com/img/2023/08/15/20230815203854-1.jpg": "2023-09-22T16:08:11+08:00",
    "http://framist-bucket-openread.oss-cn-shanghai.aliyuncs.com/img/2023/08/15/20230815203820.png": "2023-09-22T16:08:11+08:00",
    "https://pic4.zhimg.com/80/v2-a71309e3e2561ee5aac6a4031fa592e3.png": "2023-09-22T16:08:11+08:00",
    "https://pic4.zhimg.com/80/v2-cac880522a464da5ddd67bee3df4ff98.png": "2023-09-22T16:08:11+08:00",
    "https://pic4.zhimg.com/80/v2-e45ad8699b4808112fc27937afbc88d5.png": "2023-09-22T16:08:11+08:00",
    "https://pic4.zhimg.com/80/v2-1360b26dc379fb9e1a19e8ecfe686275.png": "2023-09-22T16:08:11+08:00",
    "https://pic4.zhimg.com/80/v2-0f7d7e29c3a59ee9f66734636ce47472.png": "2023-09-22T16:08:11+08:00",
    "https://blog.csdn.net/jaykm/article/details/106379447": "2023-09-22T16:08:11+08:00",
    "https://www.geeksforgeeks.org/privileged-and-non-privileged-instructions-in-operating-system": "2023-09-22T16:08:12+08:00",
    "http://framist-bucket-openread.oss-cn-shanghai.aliyuncs.com/img/2023/08/15/20230815203854-3.jpg": "2023-09-22T16:08:12+08:00",
    "http://framist-bucket-openread.oss-cn-shanghai.aliyuncs.com/img/2023/08/15/20230815203854-2.jpg": "2023-09-22T16:08:12+08:00",
    "https://www.jianshu.com/p/9f1524199860": "2023-09-22T16:08:12+08:00",
    "https://zhuanlan.zhihu.com/p/73733210": "2023-09-22T16:08:12+08:00",
    "https://zhuanlan.zhihu.com/p/73549655": "2023-09-22T16:08:12+08:00",
    "https://wangchujiang.com/linux-command/c/uptime.html": "2023-09-22T16:08:12+08:00",
    "https://zhuanlan.zhihu.com/p/64844481": "2023-09-22T16:08:13+08:00",
    "https://book.douban.com/review/5805285": "2023-09-22T16:08:13+08:00",
    "https://feichashao.com/ipc-mq": "2023-09-22T16:08:13+08:00",
    "https://book.douban.com/review/5073720": "2023-09-22T16:08:14+08:00",
    "http://framist-bucket-openread.oss-cn-shanghai.aliyuncs.com/img/2023/08/15/20230815203909-1.png": "2023-09-22T16:08:14+08:00",
    "http://framist-bucket-openread.oss-cn-shanghai.aliyuncs.com/img/2023/08/15/20230815203909-2.png": "2023-09-22T16:08:14+08:00",
    "http://framist-bucket-openread.oss-cn-shanghai.aliyuncs.com/img/2023/08/15/20230815203909.png": "2023-09-22T16:08:14+08:00",
    "http://framist-bucket-openread.oss-cn-shanghai.aliyuncs.com/img/2023/08/15/20230815203832.jpg": "2023-09-22T16:08:14+08:00",
    "https://mp.weixin.qq.com/s/cXbCd_nK4_VssJaUREiPmA": "2023-09-22T16:08:14+08:00",
    "https://blog.csdn.net/qq_37205708/article/details/86548631?spm=1001.2014.3001.5501": "2023-09-22T16:08:14+08:00",
    "https://blog.csdn.net/fanrenxiang/article/details/80623884": "2023-09-22T16:08:14+08:00",
    "https://www.zhihu.com/question/40043776/answer/1258528592": "2023-09-22T16:08:15+08:00",
    "https://blog.csdn.net/a514371309/article/details/78504974": "2023-09-22T16:08:15+08:00",
    "http://framist-bucket-openread.oss-cn-shanghai.aliyuncs.com/img/2023/08/15/20230815203902-2.gif": "2023-09-22T16:08:16+08:00",
    "http://framist-bucket-openread.oss-cn-shanghai.aliyuncs.com/img/2023/08/15/20230815203902-1.gif": "2023-09-22T16:08:16+08:00",
    "http://framist-bucket-openread.oss-cn-shanghai.aliyuncs.com/img/2023/08/15/20230815203902.jpg": "2023-09-22T16:08:16+08:00",
    "http://framist-bucket-openread.oss-cn-shanghai.aliyuncs.com/img/2023/08/15/20230815203902-3.jpg": "2023-09-22T16:08:16+08:00",
    "https://www.doc88.com/p-7334220872657.html": "2023-09-22T16:08:16+08:00",
    "http://framist-bucket-openread.oss-cn-shanghai.aliyuncs.com/img/2023/08/15/20230815203902-4.gif": "2023-09-22T16:08:16+08:00",
    "http://www.elecfans.com/emb/20180908772045.html": "2023-09-22T16:08:16+08:00",
    "https://blog.csdn.net/gengwei80/article/details/2141880": "2023-09-22T16:08:16+08:00",
    "https://blog.csdn.net/qq_32252957/article/details/84726541": "2023-09-22T16:08:16+08:00",
    "https://mermaid-js.github.io/mermaid": "2023-09-22T16:08:16+08:00",
    "https://github.com/framist/STemWinForHAL": "2023-09-22T16:09:52+08:00",
    "https://github.com/framist/E-kit": "2023-09-22T16:10:06+08:00",
    "http://framist-bucket-openread.oss-cn-shanghai.aliyuncs.com/img/2023/09/16/20230916223825.png": "2023-09-22T16:11:40+08:00",
    "http://framist-bucket-openread.oss-cn-shanghai.aliyuncs.com/img/d637541d1ea249efa4502b8dce0df959.png": "2023-09-22T16:11:40+08:00",
    "http://framist-bucket-openread.oss-cn-shanghai.aliyuncs.com/img/2023/09/16/20230916223811.jpeg": "2023-09-22T16:11:40+08:00",
    "http://framist-bucket-openread.oss-cn-shanghai.aliyuncs.com/img/c3d37b5ebb644c9f822eb975f6853a54.jpeg": "2023-09-22T16:11:40+08:00",
    "http://framist-bucket-openread.oss-cn-shanghai.aliyuncs.com/img/2023/09/16/20230916223753.jpeg": "2023-09-22T16:11:40+08:00",
    "http://framist-bucket-openread.oss-cn-shanghai.aliyuncs.com/img/113bdb48dff84122ad64f01953cfee5b.jpeg": "2023-09-22T16:11:40+08:00",
    "http://framist-bucket-openread.oss-cn-shanghai.aliyuncs.com/img/2023/09/16/20230916223808.png": "2023-09-22T16:11:40+08:00",
    "http://framist-bucket-openread.oss-cn-shanghai.aliyuncs.com/img/2023/09/16/20230916223815.jpeg": "2023-09-22T16:11:40+08:00",
    "http://framist-bucket-openread.oss-cn-shanghai.aliyuncs.com/img/2023/09/16/20230916223800.png": "2023-09-22T16:11:41+08:00",
    "https://craft.framist.top": "2023-09-22T16:11:41+08:00",
    "http://framist-bucket-openread.oss-cn-shanghai.aliyuncs.com/img/image-20230804195330067.png": "2023-09-22T16:11:41+08:00",
    "http://framist-bucket-openread.oss-cn-shanghai.aliyuncs.com/img/image-20230804203939370.png": "2023-09-22T16:11:41+08:00",
    "http://framist-bucket-openread.oss-cn-shanghai.aliyuncs.com/img/2023/09/16/20230916223818.jpeg": "2023-09-22T16:11:41+08:00",
    "http://framist-bucket-openread.oss-cn-shanghai.aliyuncs.com/img/show.png": "2023-09-22T16:11:41+08:00",
    "https://www.ti.com.cn/cn/lit/ug/zhcn005/zhcn005.pdf": "2023-09-22T16:11:41+08:00",
    "http://framist-bucket-openread.oss-cn-shanghai.aliyuncs.com/img/clip_image020.gif": "2023-09-22T16:12:23+08:00",
    "http://framist-bucket-openread.oss-cn-shanghai.aliyuncs.com/img/clip_image022.gif": "2023-09-22T16:12:23+08:00",
    "http://framist-bucket-openread.oss-cn-shanghai.aliyuncs.com/img/image-20230804203954747.png": "2023-09-22T16:12:23+08:00",
    "http://framist-bucket-openread.oss-cn-shanghai.aliyuncs.com/img/clip_image018.gif": "2023-09-22T16:12:23+08:00",
    "http://framist-bucket-openread.oss-cn-shanghai.aliyuncs.com/img/clip_image016.gif": "2023-09-22T16:12:23+08:00",
    "http://framist-bucket-openread.oss-cn-shanghai.aliyuncs.com/img/image-20230804204048568.png": "2023-09-22T16:12:23+08:00",
    "http://framist-bucket-openread.oss-cn-shanghai.aliyuncs.com/img/image-20230804204159729.png": "2023-09-22T16:12:23+08:00",
    "http://framist-bucket-openread.oss-cn-shanghai.aliyuncs.com/img/clip_image014.gif": "2023-09-22T16:12:23+08:00",
    "http://framist-bucket-openread.oss-cn-shanghai.aliyuncs.com/img/image-20230804204113005.png": "2023-09-22T16:12:23+08:00",
    "http://framist-bucket-openread.oss-cn-shanghai.aliyuncs.com/img/image-20230804204031303.png": "2023-09-22T16:12:23+08:00",
    "http://framist-bucket-openread.oss-cn-shanghai.aliyuncs.com/img/clip_image026.gif": "2023-09-22T16:12:23+08:00",
    "http://framist-bucket-openread.oss-cn-shanghai.aliyuncs.com/img/clip_image034.gif": "2023-09-22T16:12:23+08:00",
    "http://framist-bucket-openread.oss-cn-shanghai.aliyuncs.com/img/clip_image030.gif": "2023-09-22T16:12:23+08:00",
    "http://framist-bucket-openread.oss-cn-shanghai.aliyuncs.com/img/clip_image028.gif": "2023-09-22T16:12:23+08:00",
    "http://framist-bucket-openread.oss-cn-shanghai.aliyuncs.com/img/image-20230804204228254.png": "2023-09-22T16:12:23+08:00",
    "http://framist-bucket-openread.oss-cn-shanghai.aliyuncs.com/img/clip_image024.gif": "2023-09-22T16:12:23+08:00",
    "http://framist-bucket-openread.oss-cn-shanghai.aliyuncs.com/img/image-20230804200123787.png": "2023-09-22T16:12:23+08:00",
    "http://framist-bucket-openread.oss-cn-shanghai.aliyuncs.com/img/image-20230804204252245.png": "2023-09-22T16:12:23+08:00",
    "http://framist-bucket-openread.oss-cn-shanghai.aliyuncs.com/img/image-20230804200241422.png": "2023-09-22T16:12:23+08:00",
    "http://framist-bucket-openread.oss-cn-shanghai.aliyuncs.com/img/clip_image032.gif": "2023-09-22T16:12:23+08:00",
    "http://framist-bucket-openread.oss-cn-shanghai.aliyuncs.com/img/clip_image047.gif": "2023-09-22T16:12:23+08:00",
    "http://framist-bucket-openread.oss-cn-shanghai.aliyuncs.com/img/clip_image012.gif": "2023-09-22T16:12:23+08:00",
    "http://framist-bucket-openread.oss-cn-shanghai.aliyuncs.com/img/clip_image009.jpg": "2023-09-22T16:12:23+08:00",
    "http://framist-bucket-openread.oss-cn-shanghai.aliyuncs.com/img/clip_image002.gif": "2023-09-22T16:12:23+08:00",
    "http://framist-bucket-openread.oss-cn-shanghai.aliyuncs.com/img/clip_image004.jpg": "2023-09-22T16:12:23+08:00",
    "http://framist-bucket-openread.oss-cn-shanghai.aliyuncs.com/img/clip_image010.jpg": "2023-09-22T16:12:23+08:00",
    "http://framist-bucket-openread.oss-cn-shanghai.aliyuncs.com/img/clip_image045.gif": "2023-09-22T16:12:23+08:00",
    "http://framist-bucket-openread.oss-cn-shanghai.aliyuncs.com/img/image-20230804204333551.png": "2023-09-22T16:12:23+08:00",
    "http://framist-bucket-openread.oss-cn-shanghai.aliyuncs.com/img/clip_image007.jpg": "2023-09-22T16:12:24+08:00",
    "http://framist-bucket-openread.oss-cn-shanghai.aliyuncs.com/img/image-20230804204440966.png": "2023-09-22T16:12:24+08:00",
    "http://framist-bucket-openread.oss-cn-shanghai.aliyuncs.com/img/image-20230804200104422.png": "2023-09-22T16:12:24+08:00",
    "http://framist-bucket-openread.oss-cn-shanghai.aliyuncs.com/img/2023/08/15/20230815202731-1.png": "2023-09-22T16:12:24+08:00",
    "http://framist-bucket-openread.oss-cn-shanghai.aliyuncs.com/img/2023/08/15/20230815202731.png": "2023-09-22T16:12:24+08:00",
    "https://framist-bucket-openread.oss-cn-shanghai.aliyuncs.com/pdf/%E7%94%B5%E8%B5%9B%E7%BB%8F%E9%AA%8C%E5%88%86%E4%BA%AB.pdf": "2023-09-22T16:12:24+08:00",
    "https://lbsyun.baidu.com/index.php?title=webapi/guide/changeposition": "2023-09-22T16:12:24+08:00",
    "https://www.zhihu.com/people/kuang-jia-zhu-yi-zhe": "2023-09-22T16:12:24+08:00",
    "https://blog.csdn.net/weixin_47102975": "2023-09-22T16:12:24+08:00",
    "https://www.zhihu.com/question/526031956": "2023-09-22T16:12:24+08:00",
    "https://www.zhoulujun.cn/html/GIS/GIS-Science/2702.html": "2023-09-22T16:12:25+08:00",
    "https://xkcd.in/comic?lg=cn": "2023-09-22T16:12:25+08:00",
    "http://framist-bucket-openread.oss-cn-shanghai.aliyuncs.com/img/2023/09/16/20230916224310.png": "2023-09-22T16:12:25+08:00",
    "https://www.zhihu.com/question/526031956/answer/2433932128": "2023-09-22T16:12:25+08:00",
    "https://www.runoob.com/cprogramming/c-standard-library-stdarg-h.html": "2023-09-22T16:12:25+08:00",
    "https://img-blog.csdnimg.cn/img_convert/eee056570e1860594aeba972e5fe7485.jpeg": "2023-09-22T16:12:25+08:00",
    "https://pic1.zhimg.com/80/v2-04e958fd9765beb950256f043a741041_1440w.webp?source=1940ef5c": "2023-09-22T16:12:25+08:00",
    "https://www.zhihu.com/search?q=%E8%8B%B9%E6%9E%9C%E6%9C%BA%E7%A5%9E%E4%BB%99%E6%B0%B4": "2023-09-22T16:12:25+08:00",
    "https://picx.zhimg.com/80/v2-3ad46826a6103446225e1193b3246840_1440w.webp?source=1940ef5c": "2023-09-22T16:12:25+08:00",
    "https://link.zhihu.com/?target=https": "2023-09-22T16:12:25+08:00",
    "https://www.cnblogs.com/zyqgold/p/6114637.html": "2023-09-22T16:12:26+08:00",
    "https://img-blog.csdnimg.cn/img_convert/01d306bc7fa1ad2e61424892a1d9d811.png": "2023-09-22T16:13:07+08:00",
    "https://img-blog.csdnimg.cn/img_convert/6a2eacd0f2e5a7cff0b803a55858f279.png": "2023-09-22T16:13:07+08:00",
    "https://img-blog.csdnimg.cn/img_convert/84702af1f6a0a2572725744617656ecf.png": "2023-09-22T16:13:07+08:00",
    "https://img-blog.csdnimg.cn/img_convert/f9126560f3c8ae8e270c8d08f2636316.png": "2023-09-22T16:13:07+08:00",
    "https://img-blog.csdnimg.cn/img_convert/6ddb44178ee9d1ed1a6b3765a50a851a.png": "2023-09-22T16:13:07+08:00",
    "https://img-blog.csdnimg.cn/img_convert/0324f8cc602533fe2172d463d99cde15.png": "2023-09-22T16:13:07+08:00",
    "https://img-blog.csdnimg.cn/img_convert/160b1e32ac847176b4d36a117580ed28.png": "2023-09-22T16:13:07+08:00",
    "https://img-blog.csdnimg.cn/img_convert/bff66f8ab7b896259a06206235426ece.png": "2023-09-22T16:13:08+08:00",
    "https://img-blog.csdnimg.cn/img_convert/0edac69b25cd7dda634ecf0e37b6e44e.png": "2023-09-22T16:13:08+08:00",
    "https://img-blog.csdnimg.cn/img_convert/0a46d6a5fad22e5a4f335ca3aa6f9b6b.png": "2023-09-22T16:13:08+08:00",
    "https://img-blog.csdnimg.cn/img_convert/b73f951c41a86b0f815ec65eee1ca945.png": "2023-09-22T16:13:08+08:00",
    "https://img-blog.csdnimg.cn/img_convert/a7c60bdbe1a983c0eafbad6675947dd4.png": "2023-09-22T16:13:08+08:00",
    "https://img-blog.csdnimg.cn/img_convert/7fd6d0001b295bfcb6aed24ff9eb4ee1.png": "2023-09-22T16:13:08+08:00",
    "https://img-blog.csdnimg.cn/img_convert/76600d8e9d76e62c4606243c692b0879.png": "2023-09-22T16:13:08+08:00",
    "https://img-blog.csdnimg.cn/img_convert/071f7cb6a66fdc51479055d4f1b3873f.png": "2023-09-22T16:13:08+08:00",
    "https://www.zhihu.com/question/391013741/answer/1189243909": "2023-09-22T16:13:08+08:00",
    "https://img-blog.csdnimg.cn/img_convert/1e075c34e5ec6b3645104e4be1df98b9.png": "2023-09-22T16:13:08+08:00",
    "https://blog.csdn.net/qq_45805535/article/details/108416417": "2023-09-22T16:13:08+08:00",
    "https://blog.csdn.net/weixin_40851278/article/details/82701410": "2023-09-22T16:13:08+08:00",
    "https://blog.csdn.net/qq_43334196/article/details/107374390": "2023-09-22T16:13:08+08:00",
    "https://linux.cn/article-9447-1.html": "2023-09-22T16:13:08+08:00",
    "https://www.cnblogs.com/impy/p/8040684.html": "2023-09-22T16:13:09+08:00",
    "https://www.cnblogs.com/lcamry/p/5763162.html": "2023-09-22T16:13:09+08:00",
    "https://www.cnblogs.com/skyhive/p/6400989.html": "2023-09-22T16:13:09+08:00",
    "https://blog.csdn.net/bruceoxl/article/details/79151640": "2023-09-22T16:13:09+08:00",
    "https://blog.csdn.net/qq_16166591/article/details/93797976": "2023-09-22T16:13:09+08:00",
    "https://blog.csdn.net/xiajian2010/article/details/9625131": "2023-09-22T16:13:10+08:00",
    "https://mp.weixin.qq.com/s?__biz=Mzk0MjE3NDE0Ng==": "2023-09-22T16:13:12+08:00",
    "http://framist-bucket-openread.oss-cn-shanghai.aliyuncs.com/img/2023/08/15/20230815211039.png": "2023-09-22T16:13:12+08:00",
    "http://mp.weixin.qq.com/s?__biz=Mzk0MjE3NDE0Ng==": "2023-09-22T16:13:12+08:00",
    "https://www.cnblogs.com/traditional/archive/2004/01/13/9217594.html": "2023-09-22T16:13:12+08:00",
    "https://yeasy.gitbook.io/docker_practice": "2023-09-22T16:13:13+08:00",
    "https://bbs.xdsec.org/assets/files/2020-12-03/1606984383-579198-image-20201203162730743.png": "2023-09-22T16:13:13+08:00",
    "https://github.com/Audi-1/sqli-labs": "2023-09-22T16:13:13+08:00",
    "https://images2015.cnblogs.com/blog/669054/201608/669054-20160811231402125-1775048606.png": "2023-09-22T16:13:15+08:00",
    "http://framist-bucket-openread.oss-cn-shanghai.aliyuncs.com/img/2023/08/15/20230815203844.png": "2023-09-22T16:13:54+08:00",
    "https://www.jianshu.com/p/f445bfeea40a": "2023-09-22T16:13:55+08:00",
    "https://zhuanlan.zhihu.com/p/37526035": "2023-09-22T16:13:55+08:00",
    "https://www.cnblogs.com/subo_peng/p/5325326.html": "2023-09-22T16:13:55+08:00",
    "http://www.vuln.cn/6645": "2023-09-22T16:13:55+08:00",
    "http://www.vuln.cn/6643": "2023-09-22T16:13:55+08:00",
    "https://blog.csdn.net/qq_37205708/article/details/86518889": "2023-09-22T16:13:55+08:00",
    "https://www.runoob.com/w3cnote/python-func-decorators.html": "2023-09-22T16:14:37+08:00",
    "https://www.mmuaa.com/post/0c9188ffde4e2cff.html": "2023-09-22T16:14:37+08:00",
    "https://developer.aliyun.com/article/749877": "2023-09-22T16:14:37+08:00",
    "https://dormousehole.readthedocs.io/en/latest": "2023-09-22T16:14:39+08:00",
    "https://md.woooo.tech": "2023-09-22T16:14:39+08:00",
    "http://jinja.pocoo.org": "2023-09-22T16:14:40+08:00",
    "https://www.runoob.com/w3cnote/yaml-intro.html": "2023-09-22T16:15:19+08:00",
    "http://framist-bucket-openread.oss-cn-shanghai.aliyuncs.com/img/2023/08/15/20230815210748-1.png": "2023-09-22T16:15:19+08:00",
    "http://framist-bucket-openread.oss-cn-shanghai.aliyuncs.com/img/2023/08/15/20230815210748.png": "2023-09-22T16:15:19+08:00",
    "https://zhuanlan.zhihu.com/p/106057556": "2023-09-22T16:15:19+08:00",
    "https://bbs.xdsec.org/assets/files/2021-04-16/1618566972-577071-7b110100-162e-4731-b540-9baf0a72b5e4.png": "2023-09-22T16:15:20+08:00",
    "https://bbs.xdsec.org/assets/files/2021-04-13/1618302950-685600-9cf2f92c-cb5e-4522-96f9-782e5cd31410.png": "2023-09-22T16:15:20+08:00",
    "https://www.jianshu.com/p/5baf47e7c4cb": "2023-09-22T16:16:01+08:00",
    "http://framist-bucket-openread.oss-cn-shanghai.aliyuncs.com/img/2023/08/15/20230815210748-2.png": "2023-09-22T16:16:01+08:00",
    "https://cloud.tencent.com/developer/article/1477390": "2023-09-22T16:16:01+08:00",
    "https://www.nvidia.cn/geforce/guides/broadcasting-guide": "2023-09-22T16:16:01+08:00",
    "https://anhongning.blog.csdn.net/article/details/107376950": "2023-09-22T16:16:01+08:00",
    "https://blog.csdn.net/anhongning123/article/details/107378787": "2023-09-22T16:16:02+08:00",
    "https://pypi.org/project/ocrmypdf": "2023-09-22T16:16:02+08:00",
    "https://github.com/anuraghazra/github-readme-stats": "2023-09-22T16:16:23+08:00",
    "https://www.cnblogs.com/wjw-zm/p/12741055.html": "2023-09-22T16:16:43+08:00",
    "https://xz.aliyun.com/t/7519": "2023-09-22T16:16:44+08:00",
    "https://xz.aliyun.com/t/3679": "2023-09-22T16:16:44+08:00",
    "https://blog.csdn.net/qq_41107295/article/details/103026470": "2023-09-22T16:16:44+08:00",
    "https://blog.csdn.net/solitudi/article/details/107752717": "2023-09-22T16:16:44+08:00",
    "https://blog.csdn.net/csdn_Pade/article/details/88566032": "2023-09-22T16:16:44+08:00",
    "https://vim-adventures.com": "2023-09-22T16:16:44+08:00",
    "http://jsnice.org": "2023-09-22T16:16:44+08:00",
    "https://github.com/DDoSolitary/LxRunOffline/issues/150": "2023-09-22T16:16:44+08:00",
    "https://www.zhihu.com/column/CISP-PTE": "2023-09-22T16:16:44+08:00",
    "https://zhuanlan.zhihu.com/p/21367507": "2023-09-22T16:16:45+08:00",
    "https://zhuanlan.zhihu.com/p/58094104": "2023-09-22T16:16:45+08:00",
    "https://docs.python.org/zh-cn/3/library/pickletools.html": "2023-09-22T16:16:45+08:00",
    "https://blog.csdn.net/qq_43431158/article/details/108919605": "2023-09-22T16:16:45+08:00",
    "https://blog.csdn.net/qq_44657899/article/details/116272541": "2023-09-22T16:16:45+08:00",
    "https://baijiahao.baidu.com/s?id=1651247338190291435": "2023-09-22T16:16:45+08:00",
    "https://blog.csdn.net/imotherboard/category_9968803.html": "2023-09-22T16:16:45+08:00",
    "https://qiskit.org/documentation": "2023-09-22T16:16:46+08:00",
    "http://framist-bucket-openread.oss-cn-shanghai.aliyuncs.com/img/2023/08/15/20230815210519-1.png": "2023-09-22T16:17:28+08:00",
    "http://framist-bucket-openread.oss-cn-shanghai.aliyuncs.com/img/2023/08/15/20230815210519.png": "2023-09-22T16:17:28+08:00",
    "http://framist-bucket-openread.oss-cn-shanghai.aliyuncs.com/img/2023/08/15/20230815210519-3.png": "2023-09-22T16:17:28+08:00",
    "http://framist-bucket-openread.oss-cn-shanghai.aliyuncs.com/img/2023/08/15/20230815210519-2.png": "2023-09-22T16:17:28+08:00",
    "https://blog.csdn.net/lwzhang1101/article/details/78773700": "2023-09-22T16:17:28+08:00",
    "https://blog.csdn.net/weixin_44791273/article/details/108012734": "2023-09-22T16:17:28+08:00",
    "https://blog.csdn.net/qq_38412357/article/details/83212668?utm_medium=distribute.pc_relevant_t0.none-task-blog-2": "2023-09-22T16:17:28+08:00",
    "https://blog.csdn.net/qq_45698157/article/details/109746592": "2023-09-22T16:17:28+08:00",
    "http://framist-bucket-openread.oss-cn-shanghai.aliyuncs.com/img/2023/08/15/20230815210511.png": "2023-09-22T16:17:28+08:00",
    "https://www.cnblogs.com/-chenxs/p/11748488.html": "2023-09-22T16:17:28+08:00",
    "https://blog.csdn.net/qq_45924653/article/details/107445417": "2023-09-22T16:17:29+08:00",
    "https://i.loli.net/2021/05/06/KcqoT32ZrmB8ixw.png": "2023-09-22T16:17:29+08:00",
    "https://blog.csdn.net/csacs/article/details/91440568": "2023-09-22T16:17:29+08:00",
    "http://framist-bucket-openread.oss-cn-shanghai.aliyuncs.com/img/2023/08/15/20230815210527.png": "2023-09-22T16:17:33+08:00",
    "http://framist-bucket-openread.oss-cn-shanghai.aliyuncs.com/img/2023/08/15/20230815210527-1.png": "2023-09-22T16:17:33+08:00",
    "https://dawnwhisper.github.io": "2023-09-22T16:17:33+08:00",
    "https://zhuanlan.zhihu.com/p/262761814": "2023-09-22T16:17:33+08:00",
    "https://blog.csdn.net/qq_45819626/article/details/108961826": "2023-09-22T16:17:33+08:00",
    "https://noahtie.github.io/2020/10/12/MoeCTF2020": "2023-09-22T16:17:34+08:00",
    "http://framist-bucket-openread.oss-cn-shanghai.aliyuncs.com/img/2023/08/15/20230815210527-2.png": "2023-09-22T16:17:34+08:00",
    "https://www.baidu.com": "2023-09-22T16:17:34+08:00",
    "https://docs.python.org/3/library/compileall.html": "2023-09-22T16:17:34+08:00",
    "https://baike.baidu.com/item/%E9%9B%AA%E5%B4%A9%E6%95%88%E5%BA%94/13135322": "2023-09-22T16:17:34+08:00",
    "https://www.cnblogs.com/xdjun/p/7467981.html": "2023-09-22T16:17:34+08:00",
    "https://blog.csdn.net/qq_31772441/article/details/80281328": "2023-09-22T16:17:34+08:00",
    "https://pingfangx.github.io/java-tutorials/index.html": "2023-09-22T16:17:34+08:00",
    "https://blog.csdn.net/dreamer2020/article/details/52761606": "2023-09-22T16:17:36+08:00",
    "https://gameguardian.net/download": "2023-09-22T16:17:36+08:00",
    "http://framist-bucket-openread.oss-cn-shanghai.aliyuncs.com/img/2023/08/15/20230815210535.png": "2023-09-22T16:17:36+08:00",
    "http://framist-bucket-openread.oss-cn-shanghai.aliyuncs.com/img/2023/08/15/20230815210535-5.png": "2023-09-22T16:17:37+08:00",
    "http://framist-bucket-openread.oss-cn-shanghai.aliyuncs.com/img/2023/08/15/20230815210535-7.png": "2023-09-22T16:17:37+08:00",
    "http://framist-bucket-openread.oss-cn-shanghai.aliyuncs.com/img/2023/08/15/20230815210535-2.png": "2023-09-22T16:17:37+08:00",
    "http://framist-bucket-openread.oss-cn-shanghai.aliyuncs.com/img/2023/08/15/20230815210535-3.png": "2023-09-22T16:17:37+08:00",
    "http://framist-bucket-openread.oss-cn-shanghai.aliyuncs.com/img/2023/08/15/20230815210535-6.png": "2023-09-22T16:17:37+08:00",
    "http://framist-bucket-openread.oss-cn-shanghai.aliyuncs.com/img/2023/08/15/20230815210535-4.png": "2023-09-22T16:17:37+08:00",
    "http://framist-bucket-openread.oss-cn-shanghai.aliyuncs.com/img/2023/08/15/20230815210535-1.png": "2023-09-22T16:17:37+08:00",
    "https://i.loli.net/2020/07/25/rLTZdOaItNPgJnb.jpg": "2023-09-22T16:17:37+08:00",
    "https://blog.csdn.net/shahuhu000/article/details/82599134": "2023-09-22T16:17:37+08:00",
    "http://framist-bucket-openread.oss-cn-shanghai.aliyuncs.com/img/2023/08/15/20230815210535-9.png": "2023-09-22T16:17:37+08:00",
    "http://framist-bucket-openread.oss-cn-shanghai.aliyuncs.com/img/2023/08/15/20230815210535-15.png": "2023-09-22T16:17:37+08:00",
    "http://framist-bucket-openread.oss-cn-shanghai.aliyuncs.com/img/2023/08/15/20230815210535-14.png": "2023-09-22T16:17:37+08:00",
    "http://framist-bucket-openread.oss-cn-shanghai.aliyuncs.com/img/2023/08/15/20230815210535-11.png": "2023-09-22T16:17:37+08:00",
    "http://framist-bucket-openread.oss-cn-shanghai.aliyuncs.com/img/2023/08/15/20230815210535-13.png": "2023-09-22T16:17:37+08:00",
    "http://framist-bucket-openread.oss-cn-shanghai.aliyuncs.com/img/2023/08/15/20230815210535-10.png": "2023-09-22T16:17:37+08:00",
    "http://framist-bucket-openread.oss-cn-shanghai.aliyuncs.com/img/2023/08/15/20230815210535-16.png": "2023-09-22T16:17:37+08:00",
    "http://framist-bucket-openread.oss-cn-shanghai.aliyuncs.com/img/2023/08/15/20230815210535-8.png": "2023-09-22T16:17:37+08:00",
    "http://framist-bucket-openread.oss-cn-shanghai.aliyuncs.com/img/2023/08/15/20230815210535-17.png": "2023-09-22T16:17:37+08:00",
    "http://framist-bucket-openread.oss-cn-shanghai.aliyuncs.com/img/2023/08/15/20230815210535-12.png": "2023-09-22T16:17:37+08:00",
    "http://framist-bucket-openread.oss-cn-shanghai.aliyuncs.com/img/2023/08/15/20230815210535-18.png": "2023-09-22T16:17:37+08:00",
    "http://framist-bucket-openread.oss-cn-shanghai.aliyuncs.com/img/2023/08/15/20230815210535-19.png": "2023-09-22T16:17:37+08:00",
    "http://framist-bucket-openread.oss-cn-shanghai.aliyuncs.com/img/2023/08/15/20230815210547.png": "2023-09-22T16:17:37+08:00",
    "https://baike.baidu.com/item/Pwn/5321286?fr=aladdin": "2023-09-22T16:17:38+08:00",
    "http://pan-yz.chaoxing.com/share/info/01f9ea99696900b5": "2023-09-22T16:17:38+08:00",
    "https://www.luogu.com.cn": "2023-09-22T16:17:38+08:00",
    "https://www.exploit-db.com/exploits/13312": "2023-09-22T16:17:38+08:00",
    "https://wiki.x10sec.org/pwn/arm/environment": "2023-09-22T16:17:53+08:00",
    "https://developer.mozilla.org/zh-CN/docs/Web/HTTP/Methods": "2023-09-22T16:17:54+08:00",
    "https://addons.mozilla.org/zh-CN/firefox/addon/hackbar-free": "2023-09-22T16:17:55+08:00",
    "http://framist-bucket-openread.oss-cn-shanghai.aliyuncs.com/img/2023/08/15/20230815210624.png": "2023-09-22T16:18:35+08:00",
    "https://baike.baidu.com/item/%E5%AD%97%E8%8A%82/1096318": "2023-09-22T16:18:35+08:00",
    "https://baike.baidu.com/item/%E5%AF%86%E7%A0%81%E6%95%A3%E5%88%97%E5%87%BD%E6%95%B0/14937715": "2023-09-22T16:18:35+08:00",
    "https://baike.baidu.com/item/MD4/8090275": "2023-09-22T16:18:36+08:00",
    "https://baike.baidu.com/item/%E7%BD%97%E7%BA%B3%E5%BE%B7%C2%B7%E6%9D%8E%E7%BB%B4%E6%96%AF%E7%89%B9/700199": "2023-09-22T16:18:36+08:00",
    "http://www.maicaidao.com": "2023-09-22T16:18:37+08:00",
    "http://www.cmd5.com": "2023-09-22T16:19:17+08:00",
    "http://www.ttmd5.com": "2023-09-22T16:19:17+08:00",
    "http://pmd5.com": "2023-09-22T16:19:17+08:00",
    "https://baike.baidu.com/item/%E6%95%B0%E5%AD%97%E7%AD%BE%E5%90%8D/212550": "2023-09-22T16:19:17+08:00",
    "https://baike.baidu.com/item/SHA-2/22718180": "2023-09-22T16:19:18+08:00",
    "https://baike.baidu.com/item/SSL/320778": "2023-09-22T16:19:18+08:00",
    "https://wiki.x10sec.org/crypto/hash/md5": "2023-09-22T16:19:30+08:00",
    "http://ctf.ssleye.com/brain.html": "2023-09-22T16:22:21+08:00",
    "http://c.tieba.baidu.com/c/s/download/pc?src=webtbGF": "2023-09-22T16:22:21+08:00",
    "https://tieba.baidu.com/p/6870157760": "2023-09-22T16:22:22+08:00",
    "https://www.cnblogs.com/qintangtao/p/7117433.html": "2023-09-22T16:22:22+08:00",
    "https://tieba.baidu.com/f?kw=moectf": "2023-09-22T16:22:22+08:00",
    "https://tieba.baidu.com/home/main?un=%E7%8E%84%E5%BD%B1%E7%A9%BA%E7%81%B5%E6%98%9F%E7%97%95%E5%8D%B0": "2023-09-22T16:22:22+08:00",
    "https://github.com/pocmo/Python-Brainfuck": "2023-09-22T16:22:22+08:00",
    "http://www.dangermouse.net/esoteric/ook.html": "2023-09-22T16:22:24+08:00",
    "https://ourmail.cn": "2023-09-22T16:23:53+08:00",
    "http://framist-bucket-openread.oss-cn-shanghai.aliyuncs.com/img/2023/08/15/20230815210613-1.jpg": "2023-09-22T16:23:53+08:00",
    "http://framist-bucket-openread.oss-cn-shanghai.aliyuncs.com/img/2023/08/15/20230815210613.jpg": "2023-09-22T16:23:53+08:00",
    "http://pan-yz.chaoxing.com/share/info/c31dc66b18510048": "2023-09-22T16:23:53+08:00",
    "http://pan-yz.chaoxing.com/share/info/52876a078c6dbf37": "2023-09-22T16:23:53+08:00",
    "https://blog.csdn.net/ternence_hsu/article/details/89884245": "2023-09-22T16:23:54+08:00",
    "https://tieba.baidu.com/home/main?un=arttnba": "2023-09-22T16:23:54+08:00",
    "https://pan.baidu.com/s/1O9JFcsUyqQ7T85WXmHH6nQ": "2023-09-22T16:23:54+08:00",
    "http://www.jsfuck.com": "2023-09-22T16:23:54+08:00",
    "http://tiebapic.baidu.com/forum/w%3D580/sign=0876998a43e736d158138c00ab514ffc/ef31fe6134a85edf3dc929755e540923dd547525.jpg": "2023-09-22T16:23:54+08:00",
    "http://framist-bucket-openread.oss-cn-shanghai.aliyuncs.com/img/2023/08/15/20230815210613-3.jpg": "2023-09-22T16:23:54+08:00",
    "http://framist-bucket-openread.oss-cn-shanghai.aliyuncs.com/img/2023/08/15/20230815210613-2.png": "2023-09-22T16:23:54+08:00",
    "http://framist-bucket-openread.oss-cn-shanghai.aliyuncs.com/img/2023/08/15/20230815210613-7.png": "2023-09-22T16:23:54+08:00",
    "http://framist-bucket-openread.oss-cn-shanghai.aliyuncs.com/img/2023/08/15/20230815210613-4.jpg": "2023-09-22T16:23:54+08:00",
    "http://framist-bucket-openread.oss-cn-shanghai.aliyuncs.com/img/2023/08/15/20230815210613-6.png": "2023-09-22T16:23:54+08:00",
    "https://gsp0.baidu.com/5aAHeD3nKhI2p27j8IqW0jdnxx1xbK/tb/editor/images/client/image_emoticon66.png": "2023-09-22T16:23:54+08:00",
    "http://framist-bucket-openread.oss-cn-shanghai.aliyuncs.com/img/2023/08/15/20230815210613-5.jpg": "2023-09-22T16:23:54+08:00",
    "https://oss-cn-hangzhou.aliyuncs.com/myres/avatars/6347398/20200809071705?x-oss-process=style/bigavatar": "2023-09-22T16:23:54+08:00",
    "https://i.loli.net/2020/08/01/6BOZPXgsjWi48DI.jpg": "2023-09-22T16:23:55+08:00",
    "http://framist-bucket-openread.oss-cn-shanghai.aliyuncs.com/img/2023/08/15/20230815210613-9.png": "2023-09-22T16:23:55+08:00",
    "https://pic4.zhimg.com/80/v2-20ee939cdadd3c27d77356fdfd8a15dd.png": "2023-09-22T16:23:55+08:00",
    "http://framist-bucket-openread.oss-cn-shanghai.aliyuncs.com/img/2023/08/15/20230815210613-8.png": "2023-09-22T16:23:55+08:00",
    "https://pic4.zhimg.com/80/v2-3f4f4363d81b86ef2bf437a076a623fa.png": "2023-09-22T16:23:55+08:00",
    "https://ctf-wiki.org": "2023-09-22T16:23:55+08:00",
    "https://pytorch.org/tutorials/beginner/fgsm_tutorial.html": "2023-09-22T16:23:55+08:00",
    "https://i.loli.net/2020/09/02/soipQW3CyMEe6YF.png": "2023-09-22T16:23:55+08:00",
    "https://arxiv.org/abs/1412.6572": "2023-09-22T16:23:56+08:00",
    "https://github.com/pytorch/examples/tree/master/mnist": "2023-09-22T16:23:56+08:00",
    "https://i.loli.net/2020/08/21/cpQafSrMVoLJmj2.png": "2023-09-22T16:23:57+08:00",
    "https://baike.baidu.com/item/%E8%B4%B9%E9%A9%AC": "2023-09-22T16:23:57+08:00",
    "https://baike.baidu.com/item/%E6%95%B0%E8%AE%BA": "2023-09-22T16:23:57+08:00",
    "https://baike.baidu.com/item/%E8%B4%A8%E5%9B%A0%E6%95%B0/6192269": "2023-09-22T16:23:57+08:00",
    "https://baike.baidu.com/item/%E4%BA%92%E8%B4%A8": "2023-09-22T16:23:57+08:00",
    "https://baike.baidu.com/item/%E6%AD%A3%E6%95%B4%E6%95%B0": "2023-09-22T16:23:57+08:00",
    "https://blog.csdn.net/cdcq__/article/details/122370634?spm=1001.2014.3001.5502": "2023-09-22T16:23:57+08:00",
    "https://blog.csdn.net/qq_31408919/article/details/104917729": "2023-09-22T16:23:57+08:00",
    "https://blog.csdn.net/weixin_46395886/article/details/114434642": "2023-09-22T16:23:58+08:00",
    "https://www.mygeocachingprofile.com/codebreaker.vigenerecipher.aspx": "2023-09-22T16:23:58+08:00",
    "https://wiki.x10sec.org/crypto/asymmetric/rsa/rsa_theory": "2023-09-22T16:24:10+08:00",
    "https://bkimg.cdn.bcebos.com/formula/1a8b337167e4d4b2c23855d88ec4c67f.svg": "2023-09-22T16:24:10+08:00",
    "https://bkimg.cdn.bcebos.com/formula/4dee3f4df52a81983db0e3c619f96058.svg": "2023-09-22T16:24:10+08:00",
    "https://bkimg.cdn.bcebos.com/formula/f0dac18152076624d87832b62709895c.svg": "2023-09-22T16:24:10+08:00",
    "https://bkimg.cdn.bcebos.com/formula/da8649c0078a0a842779394d64011776.svg": "2023-09-22T16:24:10+08:00",
    "https://bkimg.cdn.bcebos.com/formula/5947116555169dc6fe9e3f5cdf347706.svg": "2023-09-22T16:24:10+08:00",
    "https://bkimg.cdn.bcebos.com/formula/c33d8c66364a636b051d82f0ee202a36.svg": "2023-09-22T16:24:10+08:00",
    "https://bkimg.cdn.bcebos.com/formula/679e809a0d964785d0aa4cfcb4218742.svg": "2023-09-22T16:24:10+08:00",
    "https://www.zhihu.com/equation?tex=-%5Csum_%7Bi=1%7D%5E%7Bn%7Dp_i%5Clog_%7B2%7Dp_i": "2023-09-22T16:24:10+08:00",
    "https://baike.baidu.com/item/%E7%A7%AF%E6%80%A7%E5%87%BD%E6%95%B0": "2023-09-22T16:24:10+08:00",
    "https://bkimg.cdn.bcebos.com/formula/3da31f29a8615a130216bdf28ccf3321.svg": "2023-09-22T16:24:10+08:00",
    "https://bkimg.cdn.bcebos.com/formula/b843a8b241f76d7068e96630fc384bb9.svg": "2023-09-22T16:24:10+08:00",
    "https://bkimg.cdn.bcebos.com/formula/ba40ed514646510df8a1033ff30701aa.svg": "2023-09-22T16:24:10+08:00",
    "https://bkimg.cdn.bcebos.com/formula/25e9558d577009b1b8b56f9a103b2321.svg": "2023-09-22T16:24:10+08:00",
    "https://bkimg.cdn.bcebos.com/formula/5047f2bc6e623027b7707e6c51adc92f.svg": "2023-09-22T16:24:10+08:00",
    "https://pytorch.org/docs/stable/notes/serialization.html": "2023-09-22T16:24:10+08:00",
    "https://bkimg.cdn.bcebos.com/formula/312031d1a76fa578eb4ef166530937fa.svg": "2023-09-22T16:24:10+08:00",
    "https://blog.csdn.net/KaelCui/article/details/106175313": "2023-09-22T16:24:10+08:00",
    "https://pytorch.org/docs/master/notes/autograd.html": "2023-09-22T16:24:11+08:00",
    "https://pytorch.org/tutorials/beginner/transfer_learning_tutorial.html": "2023-09-22T16:24:11+08:00",
    "https://pytorch.org/tutorials/intermediate/quantized_transfer_learning_tutorial.html": "2023-09-22T16:24:26+08:00",
    "https://pic4.zhimg.com/80/v2-2971da254a6c107ca49346dc653623a6.png": "2023-09-22T16:24:26+08:00",
    "https://pic4.zhimg.com/80/v2-3ad6c7009833d9545c7bd45238f8237a.png": "2023-09-22T16:24:26+08:00",
    "https://pic4.zhimg.com/80/v2-fbc8084144f0ebb768c138d889ebff12.png": "2023-09-22T16:24:26+08:00",
    "https://pic4.zhimg.com/80/v2-b01f0122ba537be0b683da1aef731ebc.png": "2023-09-22T16:24:26+08:00",
    "https://pic4.zhimg.com/80/v2-cc79aa5a837b2cf51fd102b5b63b5c44.png": "2023-09-22T16:24:26+08:00",
    "https://pic1.zhimg.com/v2-dfe4eaaa4450e2b58b38c5fe82f918c0_1440w.jpg?source=172ae18b": "2023-09-22T16:24:26+08:00",
    "https://pic4.zhimg.com/80/v2-d395543956ff7f9b6b1419fc7c072d64.png": "2023-09-22T16:24:26+08:00",
    "https://pic4.zhimg.com/80/v2-00f3c34164eca079658285d27057fdcc.png": "2023-09-22T16:24:26+08:00",
    "https://pic4.zhimg.com/80/v2-6391221c149e050bb1203d8ac5613fd3.png": "2023-09-22T16:24:26+08:00",
    "https://pic4.zhimg.com/80/v2-7c0d39a0eb3ba018bc59033955998a6e.png": "2023-09-22T16:24:26+08:00",
    "https://pic4.zhimg.com/80/v2-a8e3e7faf24593996366c66a77ba0a49.png": "2023-09-22T16:24:26+08:00",
    "https://pic4.zhimg.com/80/v2-8574d77b1db308b36e2e4586ddc2f033.png": "2023-09-22T16:24:26+08:00",
    "https://blog.csdn.net/weixin_47102975/article/details/126823212": "2023-09-22T16:24:27+08:00",
    "https://blog.csdn.net/weixin_47102975/article/details/126823202": "2023-09-22T16:24:27+08:00",
    "https://blog.csdn.net/weixin_47102975/article/details/126822467": "2023-09-22T16:24:27+08:00",
    "https://blog.csdn.net/weixin_47102975/article/details/126822398": "2023-09-22T16:24:27+08:00",
    "https://blog.csdn.net/weixin_47102975/article/details/126823172": "2023-09-22T16:24:27+08:00",
    "https://blog.csdn.net/weixin_47102975/article/details/126822624": "2023-09-22T16:24:27+08:00",
    "https://blog.csdn.net/weixin_47102975/article/details/126822598": "2023-09-22T16:24:27+08:00",
    "https://blog.csdn.net/weixin_47102975/article/details/126822502": "2023-09-22T16:24:27+08:00",
    "https://pic4.zhimg.com/80/v2-17ba13d53e49ec05521c1d8dd16013c1.png": "2023-09-22T16:24:27+08:00",
    "https://pic4.zhimg.com/80/v2-523ab6128d6c53d422a732896477d2f2.png": "2023-09-22T16:24:27+08:00",
    "https://pic4.zhimg.com/80/v2-722917acd9a52369595d6b90dc043037.png": "2023-09-22T16:24:27+08:00"
}